{
  "CallSummary": {
    "CallsLastHour": 0, 
    "CustomerCalls": 0
  }, 
  "Outages": [
    {
      "Verified": true, 
      "TroubledElement": null, 
      "CustomersServed": null, 
      "Actions": null, 
      "Status": null, 
      "District": null, 
      "SuspectedCause": null, 
      "CustomersOutNow": 1, 
      "CrewResponsible": null, 
      "CustomerResponsible": null, 
      "OutagedPhase": null, 
      "CustomersAffected": null, 
      "OutageStartTime": "2017-09-14T06:06:41-04:00", 
      "Dispatcher": null, 
      "Substation": null, 
      "UplineElement": null, 
      "OutageStatus": null, 
      "EstimatedTime": null, 
      "Notes": null, 
      "CrewDispatched": true, 
      "VerifiedCause": null, 
      "CostEstimate": null, 
      "CustomersRestored": 0, 
      "PriorityCustomers": null, 
      "CustomersOutInitially": null, 
      "OutageRecID": "2017-09-14-0847", 
      "OutageName": "6712042000 53 Spur", 
      "OutageEndTime": null, 
      "ClosingDispatcher": null, 
      "OutageLocation": {
        "Y": 34.4694020613598, 
        "X": -84.97364034601675
      }, 
      "Feeder": null, 
      "OutagePolygon": [], 
      "MapLocation": null
    }, 
    {
      "Verified": true, 
      "TroubledElement": null, 
      "CustomersServed": null, 
      "Actions": null, 
      "Status": null, 
      "District": null, 
      "SuspectedCause": null, 
      "CustomersOutNow": 33, 
      "CrewResponsible": null, 
      "CustomerResponsible": null, 
      "OutagedPhase": null, 
      "CustomersAffected": null, 
      "OutageStartTime": "2017-09-14T12:59:17-04:00", 
      "Dispatcher": null, 
      "Substation": null, 
      "UplineElement": null, 
      "OutageStatus": null, 
      "EstimatedTime": null, 
      "Notes": null, 
      "CrewDispatched": true, 
      "VerifiedCause": null, 
      "CostEstimate": null, 
      "CustomersRestored": 0, 
      "PriorityCustomers": null, 
      "CustomersOutInitially": null, 
      "OutageRecID": "2017-09-14-0871", 
      "OutageName": "F2516504", 
      "OutageEndTime": null, 
      "ClosingDispatcher": null, 
      "OutageLocation": {
        "Y": 34.59375012382116, 
        "X": -85.39309730262481
      }, 
      "Feeder": null, 
      "OutagePolygon": [
        {
          "Y": 34.56774203101574, 
          "X": -85.41390358924222
        }, 
        {
          "Y": 34.602426957869135, 
          "X": -85.39762812373306
        }, 
        {
          "Y": 34.60531948869183, 
          "X": -85.38718517273605
        }, 
        {
          "Y": 34.604395221234036, 
          "X": -85.3863041279158
        }, 
        {
          "Y": 34.60262061673704, 
          "X": -85.38624458808965
        }, 
        {
          "Y": 34.5880658578239, 
          "X": -85.3888678727637
        }, 
        {
          "Y": 34.58568069337643, 
          "X": -85.39154764389303
        }
      ], 
      "MapLocation": null
    }, 
    {
      "Verified": false, 
      "TroubledElement": null, 
      "CustomersServed": null, 
      "Actions": null, 
      "Status": null, 
      "District": null, 
      "SuspectedCause": null, 
      "CustomersOutNow": 2, 
      "CrewResponsible": null, 
      "CustomerResponsible": null, 
      "OutagedPhase": null, 
      "CustomersAffected": null, 
      "OutageStartTime": "2017-09-14T13:26:07-04:00", 
      "Dispatcher": null, 
      "Substation": null, 
      "UplineElement": null, 
      "OutageStatus": null, 
      "EstimatedTime": null, 
      "Notes": null, 
      "CrewDispatched": true, 
      "VerifiedCause": null, 
      "CostEstimate": null, 
      "CustomersRestored": 0, 
      "PriorityCustomers": null, 
      "CustomersOutInitially": null, 
      "OutageRecID": "2017-09-14-0873", 
      "OutageName": "T7306060", 
      "OutageEndTime": null, 
      "ClosingDispatcher": null, 
      "OutageLocation": {
        "Y": 34.77301574043997, 
        "X": -84.8906959927706
      }, 
      "Feeder": null, 
      "OutagePolygon": [
        {
          "Y": 34.77288995888688, 
          "X": -84.89077913135311
        }, 
        {
          "Y": 34.77314152199306, 
          "X": -84.89061285418809
        }
      ], 
      "MapLocation": null
    }
  ], 
  "Trucks": [], 
  "Areas": [
    {
      "County": "Chattooga", 
      "Count": 12
    }, 
    {
      "County": "Gordon", 
      "Count": 1
    }, 
    {
      "County": "Walker", 
      "Count": 21
    }, 
    {
      "County": "Whitfield", 
      "Count": 2
    }
  ]
}