[
  {
    "hazardFlag": "1", 
    "lastUpdateTime": "1508641000", 
    "estCustAffected": "1", 
    "crewCurrentStatus": "PG&E is sending a repair crew to the outage location.", 
    "longitude": "-122.45678", 
    "latitude": "38.57782", 
    "outageStartTime": "1508619388", 
    "cause": "Field personnel have found a downed power line.", 
    "outageNumber": "1906853", 
    "regionName": "Angwin"
  }, 
  {
    "hazardFlag": "0", 
    "longitude": "-121.82367", 
    "lastUpdateTime": "1508687650", 
    "estCustAffected": "15", 
    "crewCurrentStatus": "PG&E is assessing the cause at the outage location.", 
    "crewEta": "1508678220", 
    "latitude": "38.00466", 
    "outageStartTime": "1508667953", 
    "cause": "Unknown - PG&E is investigating the cause.", 
    "outageNumber": "1907103", 
    "regionName": "Antioch"
  }, 
  {
    "currentEtor": "1508709600", 
    "outageDevices": [
      {
        "latitude": "35.18949", 
        "longitude": "-120.71638"
      }, 
      {
        "latitude": "35.19406", 
        "longitude": "-120.71541"
      }, 
      {
        "latitude": "35.19663", 
        "longitude": "-120.71854"
      }, 
      {
        "latitude": "35.19767", 
        "longitude": "-120.72259"
      }, 
      {
        "latitude": "35.19655", 
        "longitude": "-120.72203"
      }, 
      {
        "latitude": "35.18984", 
        "longitude": "-120.71771"
      }
    ], 
    "hazardFlag": "1", 
    "lastUpdateTime": "1508669687", 
    "estCustAffected": "105", 
    "crewCurrentStatus": "PG&E repair crew is on-site working to restore power.", 
    "longitude": "-120.70429", 
    "latitude": "35.18458", 
    "outageStartTime": "1508651400", 
    "cause": "Found damaged equipment.", 
    "outageNumber": "1907082", 
    "regionName": "Avilla Beach"
  }, 
  {
    "hazardFlag": "0", 
    "longitude": "-118.98894", 
    "lastUpdateTime": "1508686685", 
    "estCustAffected": "1", 
    "crewCurrentStatus": "PG&E is assessing the cause at the outage location.", 
    "crewEta": "1508687700", 
    "latitude": "35.35076", 
    "outageStartTime": "1508684160", 
    "cause": "Unknown - PG&E is investigating the cause.", 
    "outageNumber": "1907124", 
    "regionName": "Bakersfield"
  }, 
  {
    "currentEtor": "1508738400", 
    "outageDevices": [
      {
        "latitude": "38.63865", 
        "longitude": "-122.65668"
      }, 
      {
        "latitude": "38.63988", 
        "longitude": "-122.64589"
      }, 
      {
        "latitude": "38.64088", 
        "longitude": "-122.64332"
      }
    ], 
    "hazardFlag": "0", 
    "lastUpdateTime": "1508624705", 
    "estCustAffected": "2", 
    "crewCurrentStatus": "PG&E repair crew is on-site working to restore power.", 
    "longitude": "-122.6683", 
    "latitude": "38.62953", 
    "outageStartTime": "1507523605", 
    "cause": "Fire in the area.", 
    "outageNumber": "1903598", 
    "regionName": "Calistoga"
  }, 
  {
    "currentEtor": "1508828340", 
    "outageDevices": [
      {
        "latitude": "38.56573", 
        "longitude": "-122.64376"
      }, 
      {
        "latitude": "38.56957", 
        "longitude": "-122.64638"
      }, 
      {
        "latitude": "38.57058", 
        "longitude": "-122.65165"
      }, 
      {
        "latitude": "38.56875", 
        "longitude": "-122.65787"
      }, 
      {
        "latitude": "38.56834", 
        "longitude": "-122.65892"
      }, 
      {
        "latitude": "38.56763", 
        "longitude": "-122.65771"
      }
    ], 
    "hazardFlag": "0", 
    "longitude": "-122.64879", 
    "lastUpdateTime": "1508682857", 
    "crewEta": "1508442660", 
    "crewCurrentStatus": "PG&E repair crew is on-site working to restore power.", 
    "estCustAffected": "26", 
    "latitude": "38.57188", 
    "outageStartTime": "1507530195", 
    "cause": "Found a broken power pole in the area", 
    "outageNumber": "1902262", 
    "regionName": "Calistoga"
  }, 
  {
    "currentEtor": "1508738400", 
    "hazardFlag": "0", 
    "lastUpdateTime": "1508611810", 
    "estCustAffected": "1", 
    "crewCurrentStatus": "PG&E repair crew is on-site working to restore power.", 
    "longitude": "-122.61956", 
    "latitude": "38.5992", 
    "outageStartTime": "1507521110", 
    "cause": "Found damaged equipment on a power pole.", 
    "outageNumber": "1898727", 
    "regionName": "Calistoga"
  }, 
  {
    "hazardFlag": "0", 
    "lastUpdateTime": "1508584321", 
    "estCustAffected": "2", 
    "crewCurrentStatus": "PG&E is sending a repair crew to the outage location.", 
    "longitude": "-122.66489", 
    "latitude": "38.55527", 
    "outageStartTime": "1507529829", 
    "cause": "Found a broken power pole in the area", 
    "outageNumber": "1906243", 
    "regionName": "Calistoga"
  }, 
  {
    "currentEtor": "1508741940", 
    "outageDevices": [
      {
        "latitude": "38.56825", 
        "longitude": "-122.58154"
      }, 
      {
        "latitude": "38.57155", 
        "longitude": "-122.58193"
      }, 
      {
        "latitude": "38.57363", 
        "longitude": "-122.58719"
      }, 
      {
        "latitude": "38.57332", 
        "longitude": "-122.58835"
      }, 
      {
        "latitude": "38.56897", 
        "longitude": "-122.58604"
      }
    ], 
    "hazardFlag": "0", 
    "lastUpdateTime": "1508631427", 
    "estCustAffected": "20", 
    "crewCurrentStatus": "PG&E repair crew is on-site working to restore power.", 
    "longitude": "-122.5786", 
    "latitude": "38.59241", 
    "outageStartTime": "1507548600", 
    "cause": "Fire in the area.", 
    "outageNumber": "1898937", 
    "regionName": "Calistoga"
  }, 
  {
    "currentEtor": "1508738400", 
    "hazardFlag": "0", 
    "lastUpdateTime": "1508624980", 
    "estCustAffected": "4", 
    "crewCurrentStatus": "PG&E repair crew is on-site working to restore power.", 
    "longitude": "-122.6272", 
    "latitude": "38.60136", 
    "outageStartTime": "1507521110", 
    "cause": "Fire in the area.", 
    "outageNumber": "1904304", 
    "regionName": "Calistoga"
  }, 
  {
    "currentEtor": "1508741940", 
    "hazardFlag": "0", 
    "lastUpdateTime": "1508521318", 
    "estCustAffected": "1", 
    "crewCurrentStatus": "PG&E repair crew is on-site working to restore power.", 
    "longitude": "-122.64866", 
    "latitude": "38.56631", 
    "outageStartTime": "1507530195", 
    "cause": "Fire in the area.", 
    "outageNumber": "1902091", 
    "regionName": "Calistoga"
  }, 
  {
    "currentEtor": "1508741940", 
    "outageDevices": [
      {
        "latitude": "38.60624", 
        "longitude": "-122.67345"
      }, 
      {
        "latitude": "38.61835", 
        "longitude": "-122.65394"
      }, 
      {
        "latitude": "38.62156", 
        "longitude": "-122.65208"
      }, 
      {
        "latitude": "38.63445", 
        "longitude": "-122.67086"
      }, 
      {
        "latitude": "38.62994", 
        "longitude": "-122.6828"
      }, 
      {
        "latitude": "38.61916", 
        "longitude": "-122.69366"
      }, 
      {
        "latitude": "38.60911", 
        "longitude": "-122.6947"
      }
    ], 
    "hazardFlag": "4", 
    "lastUpdateTime": "1508543308", 
    "estCustAffected": "79", 
    "crewCurrentStatus": "PG&E repair crew is on-site working to restore power.", 
    "longitude": "-122.65845", 
    "latitude": "38.61578", 
    "outageStartTime": "1507523605", 
    "cause": "Fire in the area.", 
    "outageNumber": "1893951", 
    "regionName": "Calistoga"
  }, 
  {
    "currentEtor": "1508742060", 
    "hazardFlag": "0", 
    "lastUpdateTime": "1508624331", 
    "estCustAffected": "2", 
    "crewCurrentStatus": "PG&E is sending a repair crew to the outage location.", 
    "longitude": "-122.59503", 
    "latitude": "38.61859", 
    "outageStartTime": "1507548600", 
    "cause": "Fire in the area.", 
    "outageNumber": "1901302", 
    "regionName": "Calistoga"
  }, 
  {
    "currentEtor": "1508738400", 
    "outageDevices": [
      {
        "latitude": "38.6008", 
        "longitude": "-122.60312"
      }, 
      {
        "latitude": "38.60092", 
        "longitude": "-122.59951"
      }, 
      {
        "latitude": "38.60904", 
        "longitude": "-122.59479"
      }, 
      {
        "latitude": "38.60976", 
        "longitude": "-122.59562"
      }, 
      {
        "latitude": "38.61087", 
        "longitude": "-122.59859"
      }, 
      {
        "latitude": "38.60858", 
        "longitude": "-122.60217"
      }, 
      {
        "latitude": "38.60512", 
        "longitude": "-122.60582"
      }
    ], 
    "hazardFlag": "0", 
    "longitude": "-122.59908", 
    "lastUpdateTime": "1508548428", 
    "crewEta": "1508367360", 
    "crewCurrentStatus": "PG&E repair crew is on-site working to restore power.", 
    "estCustAffected": "12", 
    "latitude": "38.60031", 
    "outageStartTime": "1508094105", 
    "cause": "Fire in the area.", 
    "outageNumber": "1901305", 
    "regionName": "Calistoga"
  }, 
  {
    "currentEtor": "1508824800", 
    "outageDevices": [
      {
        "latitude": "38.56707", 
        "longitude": "-122.63265"
      }, 
      {
        "latitude": "38.57059", 
        "longitude": "-122.63184"
      }, 
      {
        "latitude": "38.58142", 
        "longitude": "-122.64105"
      }, 
      {
        "latitude": "38.5833", 
        "longitude": "-122.64452"
      }, 
      {
        "latitude": "38.59367", 
        "longitude": "-122.67692"
      }, 
      {
        "latitude": "38.59474", 
        "longitude": "-122.682"
      }, 
      {
        "latitude": "38.59215", 
        "longitude": "-122.68292"
      }, 
      {
        "latitude": "38.58445", 
        "longitude": "-122.68449"
      }, 
      {
        "latitude": "38.56921", 
        "longitude": "-122.67471"
      }, 
      {
        "latitude": "38.5687", 
        "longitude": "-122.671"
      }
    ], 
    "hazardFlag": "1", 
    "lastUpdateTime": "1508682826", 
    "estCustAffected": "134", 
    "crewCurrentStatus": "PG&E repair crew is on-site working to restore power.", 
    "longitude": "-122.6299", 
    "latitude": "38.56671", 
    "outageStartTime": "1507530195", 
    "cause": "Found damaged equipment on a power pole.", 
    "outageNumber": "1903609", 
    "regionName": "Calistoga"
  }, 
  {
    "currentEtor": "1508824800", 
    "outageDevices": [
      {
        "latitude": "38.57611", 
        "longitude": "-122.62354"
      }, 
      {
        "latitude": "38.58076", 
        "longitude": "-122.62501"
      }, 
      {
        "latitude": "38.58054", 
        "longitude": "-122.62687"
      }, 
      {
        "latitude": "38.57739", 
        "longitude": "-122.6256"
      }
    ], 
    "hazardFlag": "2", 
    "longitude": "-122.62303", 
    "lastUpdateTime": "1508682876", 
    "crewEta": "1508457660", 
    "crewCurrentStatus": "PG&E repair crew is on-site working to restore power.", 
    "estCustAffected": "7", 
    "latitude": "38.57552", 
    "outageStartTime": "1507530195", 
    "cause": "Found a broken power pole in the area", 
    "outageNumber": "1903607", 
    "regionName": "Calistoga"
  }, 
  {
    "currentEtor": "1508738400", 
    "outageDevices": [
      {
        "latitude": "38.6313", 
        "longitude": "-122.74567"
      }, 
      {
        "latitude": "38.6327", 
        "longitude": "-122.67442"
      }, 
      {
        "latitude": "38.63783", 
        "longitude": "-122.66758"
      }, 
      {
        "latitude": "38.68137", 
        "longitude": "-122.73134"
      }, 
      {
        "latitude": "38.68053", 
        "longitude": "-122.73366"
      }, 
      {
        "latitude": "38.67288", 
        "longitude": "-122.74675"
      }, 
      {
        "latitude": "38.67259", 
        "longitude": "-122.74709"
      }, 
      {
        "latitude": "38.64171", 
        "longitude": "-122.75172"
      }
    ], 
    "hazardFlag": "3", 
    "lastUpdateTime": "1508605495", 
    "estCustAffected": "76", 
    "crewCurrentStatus": "PG&E repair crew is on-site working to restore power.", 
    "longitude": "-122.67438", 
    "latitude": "38.63268", 
    "outageStartTime": "1507513260", 
    "cause": "Field personnel have found a downed power line.", 
    "outageNumber": "1893704", 
    "regionName": "Calistoga"
  }, 
  {
    "currentEtor": "1508806800", 
    "outageDevices": [
      {
        "latitude": "38.59459", 
        "longitude": "-122.62387"
      }, 
      {
        "latitude": "38.59553", 
        "longitude": "-122.62307"
      }, 
      {
        "latitude": "38.60225", 
        "longitude": "-122.62173"
      }, 
      {
        "latitude": "38.6031", 
        "longitude": "-122.62315"
      }, 
      {
        "latitude": "38.59627", 
        "longitude": "-122.62424"
      }, 
      {
        "latitude": "38.59498", 
        "longitude": "-122.62413"
      }
    ], 
    "hazardFlag": "0", 
    "lastUpdateTime": "1508682898", 
    "estCustAffected": "15", 
    "crewCurrentStatus": "PG&E repair crew is on-site working to restore power.", 
    "longitude": "-122.61936", 
    "latitude": "38.59871", 
    "outageStartTime": "1507521110", 
    "cause": "Found a damaged power pole in the area.", 
    "outageNumber": "1898924", 
    "regionName": "Calistoga"
  }, 
  {
    "currentEtor": "1508738400", 
    "hazardFlag": "0", 
    "lastUpdateTime": "1508619777", 
    "estCustAffected": "2", 
    "crewCurrentStatus": "PG&E repair crew is on-site working to restore power.", 
    "longitude": "-122.61933", 
    "latitude": "38.59949", 
    "outageStartTime": "1507521110", 
    "cause": "Fire in the area.", 
    "outageNumber": "1898920", 
    "regionName": "Calistoga"
  }, 
  {
    "currentEtor": "1508824800", 
    "hazardFlag": "0", 
    "lastUpdateTime": "1508682892", 
    "estCustAffected": "2", 
    "crewCurrentStatus": "PG&E repair crew is on-site working to restore power.", 
    "longitude": "-122.63569", 
    "latitude": "38.56763", 
    "outageStartTime": "1507530195", 
    "cause": "Fire in the area.", 
    "outageNumber": "1903613", 
    "regionName": "Calistoga"
  }, 
  {
    "currentEtor": "1508731200", 
    "hazardFlag": "0", 
    "lastUpdateTime": "1508678890", 
    "estCustAffected": "3", 
    "crewCurrentStatus": "PG&E repair crew is on-site working to restore power.", 
    "longitude": "-122.65505", 
    "latitude": "38.55409", 
    "outageStartTime": "1507529829", 
    "cause": "Fire in the area.", 
    "outageNumber": "1902655", 
    "regionName": "Calistoga"
  }, 
  {
    "currentEtor": "1508741940", 
    "hazardFlag": "0", 
    "lastUpdateTime": "1508521349", 
    "estCustAffected": "1", 
    "crewCurrentStatus": "PG&E repair crew is on-site working to restore power.", 
    "longitude": "-122.6272", 
    "latitude": "38.59885", 
    "outageStartTime": "1507521110", 
    "cause": "Fire in the area.", 
    "outageNumber": "1902053", 
    "regionName": "Calistoga"
  }, 
  {
    "currentEtor": "1508741940", 
    "hazardFlag": "0", 
    "lastUpdateTime": "1508521228", 
    "estCustAffected": "1", 
    "crewCurrentStatus": "PG&E repair crew is on-site working to restore power.", 
    "longitude": "-122.62635", 
    "latitude": "38.59939", 
    "outageStartTime": "1507521110", 
    "cause": "Fire in the area.", 
    "outageNumber": "1902051", 
    "regionName": "Calistoga"
  }, 
  {
    "currentEtor": "1508806800", 
    "outageDevices": [
      {
        "latitude": "38.58059", 
        "longitude": "-122.63478"
      }, 
      {
        "latitude": "38.58233", 
        "longitude": "-122.61172"
      }, 
      {
        "latitude": "38.58699", 
        "longitude": "-122.61179"
      }, 
      {
        "latitude": "38.59304", 
        "longitude": "-122.64748"
      }, 
      {
        "latitude": "38.59139", 
        "longitude": "-122.65023"
      }, 
      {
        "latitude": "38.5817", 
        "longitude": "-122.63692"
      }
    ], 
    "hazardFlag": "1", 
    "lastUpdateTime": "1508682842", 
    "estCustAffected": "42", 
    "crewCurrentStatus": "PG&E repair crew is on-site working to restore power.", 
    "longitude": "-122.59787", 
    "latitude": "38.58033", 
    "outageStartTime": "1507546200", 
    "cause": "Fire in the area.", 
    "outageNumber": "1895616", 
    "regionName": "Calistoga"
  }, 
  {
    "currentEtor": "1508741940", 
    "hazardFlag": "0", 
    "lastUpdateTime": "1508521248", 
    "estCustAffected": "1", 
    "crewCurrentStatus": "PG&E repair crew is on-site working to restore power.", 
    "longitude": "-122.62571", 
    "latitude": "38.60074", 
    "outageStartTime": "1507521110", 
    "cause": "Fire in the area.", 
    "outageNumber": "1902050", 
    "regionName": "Calistoga"
  }, 
  {
    "currentEtor": "1508738400", 
    "outageDevices": [
      {
        "latitude": "38.59843", 
        "longitude": "-122.64369"
      }, 
      {
        "latitude": "38.59881", 
        "longitude": "-122.62231"
      }, 
      {
        "latitude": "38.6046", 
        "longitude": "-122.6241"
      }, 
      {
        "latitude": "38.60664", 
        "longitude": "-122.62678"
      }, 
      {
        "latitude": "38.6148", 
        "longitude": "-122.6515"
      }, 
      {
        "latitude": "38.61574", 
        "longitude": "-122.65444"
      }, 
      {
        "latitude": "38.61519", 
        "longitude": "-122.65843"
      }, 
      {
        "latitude": "38.61261", 
        "longitude": "-122.66124"
      }, 
      {
        "latitude": "38.60819", 
        "longitude": "-122.66259"
      }, 
      {
        "latitude": "38.60506", 
        "longitude": "-122.66346"
      }, 
      {
        "latitude": "38.59961", 
        "longitude": "-122.65674"
      }
    ], 
    "hazardFlag": "4", 
    "lastUpdateTime": "1508528603", 
    "estCustAffected": "74", 
    "crewCurrentStatus": "PG&E repair crew is on-site working to restore power.", 
    "longitude": "-122.62017", 
    "latitude": "38.59884", 
    "outageStartTime": "1507521110", 
    "cause": "Fire in the area.", 
    "outageNumber": "1902716", 
    "regionName": "Calistoga"
  }, 
  {
    "currentEtor": "1508731200", 
    "hazardFlag": "0", 
    "lastUpdateTime": "1508678910", 
    "estCustAffected": "4", 
    "crewCurrentStatus": "PG&E repair crew is on-site working to restore power.", 
    "longitude": "-122.65538", 
    "latitude": "38.55409", 
    "outageStartTime": "1507529829", 
    "cause": "Fire in the area.", 
    "outageNumber": "1902648", 
    "regionName": "Calistoga"
  }, 
  {
    "currentEtor": "1508738400", 
    "hazardFlag": "0", 
    "lastUpdateTime": "1508624672", 
    "estCustAffected": "2", 
    "crewCurrentStatus": "PG&E repair crew is on-site working to restore power.", 
    "longitude": "-122.64702", 
    "latitude": "38.64111", 
    "outageStartTime": "1507523605", 
    "cause": "Fire in the area.", 
    "outageNumber": "1903474", 
    "regionName": "Calistoga"
  }, 
  {
    "currentEtor": "1508738400", 
    "hazardFlag": "0", 
    "lastUpdateTime": "1508521194", 
    "estCustAffected": "3", 
    "crewCurrentStatus": "PG&E repair crew is on-site working to restore power.", 
    "longitude": "-122.62568", 
    "latitude": "38.60011", 
    "outageStartTime": "1507521110", 
    "cause": "Fire in the area.", 
    "outageNumber": "1901314", 
    "regionName": "Calistoga"
  }, 
  {
    "currentEtor": "1508693640", 
    "hazardFlag": "1", 
    "lastUpdateTime": "1508686459", 
    "estCustAffected": "1", 
    "crewCurrentStatus": "PG&E repair crew is on-site working to restore power.", 
    "longitude": "-120.67796", 
    "latitude": "38.73838", 
    "outageStartTime": "1508646980", 
    "cause": "There is a problem with the transformer.", 
    "outageNumber": "1907076", 
    "regionName": "Camino"
  }, 
  {
    "currentEtor": "1508727600", 
    "outageDevices": [
      {
        "latitude": "38.7747", 
        "longitude": "-122.90382"
      }, 
      {
        "latitude": "38.77545", 
        "longitude": "-122.9"
      }, 
      {
        "latitude": "38.77752", 
        "longitude": "-122.91087"
      }
    ], 
    "hazardFlag": "0", 
    "lastUpdateTime": "1508602262", 
    "estCustAffected": "3", 
    "crewCurrentStatus": "PG&E is unable to access the affected equipment.", 
    "longitude": "-122.98103", 
    "latitude": "38.77624", 
    "outageStartTime": "1507530480", 
    "cause": "Found a damaged power pole in the area.", 
    "outageNumber": "1894573", 
    "regionName": "Cloverdale"
  }, 
  {
    "hazardFlag": "0", 
    "lastUpdateTime": "1508687159", 
    "estCustAffected": "1", 
    "crewCurrentStatus": "PG&E is assessing the cause at the outage location.", 
    "longitude": "-122.51832", 
    "latitude": "37.93667", 
    "outageStartTime": "1508684815", 
    "cause": "Unknown - PG&E is investigating the cause.", 
    "outageNumber": "1907129", 
    "regionName": "Corte Madera"
  }, 
  {
    "currentEtor": "1508698800", 
    "hazardFlag": "0", 
    "lastUpdateTime": "1508687417", 
    "autoEtor": "1508698800", 
    "estCustAffected": "1", 
    "crewCurrentStatus": "PG&E has assigned a crew to assess the outage.", 
    "longitude": "-121.71252", 
    "latitude": "38.33662", 
    "outageStartTime": "1508687400", 
    "cause": "Unknown - PG&E will be assessing the cause.", 
    "outageNumber": "1907137", 
    "regionName": "Dixon"
  }, 
  {
    "currentEtor": "1508695200", 
    "hazardFlag": "1", 
    "lastUpdateTime": "1508686103", 
    "autoEtor": "1508695200", 
    "estCustAffected": "1", 
    "crewCurrentStatus": "PG&E assessment crew is en route to the outage.", 
    "longitude": "-120.62009", 
    "latitude": "35.65196", 
    "outageStartTime": "1508684094", 
    "cause": "Unknown - PG&E will be assessing the cause.", 
    "outageNumber": "1907123", 
    "regionName": "El Paso de Robles (Paso Robles)"
  }, 
  {
    "currentEtor": "1508673600", 
    "hazardFlag": "0", 
    "lastUpdateTime": "1508664730", 
    "estCustAffected": "1", 
    "crewCurrentStatus": "PG&E is sending a repair crew to the outage location.", 
    "longitude": "-123.98654", 
    "latitude": "40.14518", 
    "outageStartTime": "1508624040", 
    "cause": "There is a problem with the transformer.", 
    "outageNumber": "1906913", 
    "regionName": "Garberville"
  }, 
  {
    "outageDevices": [
      {
        "latitude": "38.77302", 
        "longitude": "-122.89656"
      }, 
      {
        "latitude": "38.77878", 
        "longitude": "-122.89287"
      }, 
      {
        "latitude": "38.78077", 
        "longitude": "-122.89359"
      }, 
      {
        "latitude": "38.77657", 
        "longitude": "-122.89727"
      }
    ], 
    "hazardFlag": "0", 
    "lastUpdateTime": "1508545480", 
    "estCustAffected": "7", 
    "crewCurrentStatus": "PG&E is sending a repair crew to the outage location.", 
    "longitude": "-122.89838", 
    "latitude": "38.77556", 
    "outageStartTime": "1507530480", 
    "cause": "Found a broken power pole in the area", 
    "outageNumber": "1906431", 
    "regionName": "Geyserville"
  }, 
  {
    "outageDevices": [
      {
        "latitude": "38.75047", 
        "longitude": "-122.9092"
      }, 
      {
        "latitude": "38.75786", 
        "longitude": "-122.89593"
      }, 
      {
        "latitude": "38.7655", 
        "longitude": "-122.89577"
      }, 
      {
        "latitude": "38.76697", 
        "longitude": "-122.89636"
      }, 
      {
        "latitude": "38.76973", 
        "longitude": "-122.90502"
      }, 
      {
        "latitude": "38.76466", 
        "longitude": "-122.90834"
      }, 
      {
        "latitude": "38.76045", 
        "longitude": "-122.91097"
      }
    ], 
    "hazardFlag": "3", 
    "lastUpdateTime": "1508603545", 
    "estCustAffected": "26", 
    "crewCurrentStatus": "PG&E is sending a repair crew to the outage location.", 
    "longitude": "-122.9082", 
    "latitude": "38.77298", 
    "outageStartTime": "1507530480", 
    "cause": "Unplanned emergency repairs.", 
    "outageNumber": "1906698", 
    "regionName": "Geyserville"
  }, 
  {
    "currentEtor": "1508720400", 
    "outageDevices": [
      {
        "latitude": "38.78429", 
        "longitude": "-122.82199"
      }, 
      {
        "latitude": "38.80018", 
        "longitude": "-122.83213"
      }, 
      {
        "latitude": "38.80774", 
        "longitude": "-122.84595"
      }, 
      {
        "latitude": "38.82676", 
        "longitude": "-122.88989"
      }, 
      {
        "latitude": "38.82877", 
        "longitude": "-122.89662"
      }, 
      {
        "latitude": "38.8289", 
        "longitude": "-122.89722"
      }, 
      {
        "latitude": "38.82321", 
        "longitude": "-122.88993"
      }
    ], 
    "hazardFlag": "0", 
    "lastUpdateTime": "1508678449", 
    "estCustAffected": "12", 
    "crewCurrentStatus": "PG&E is sending a repair crew to the outage location.", 
    "longitude": "-122.82028", 
    "latitude": "38.77638", 
    "outageStartTime": "1508193581", 
    "cause": "Found a broken power pole in the area", 
    "outageNumber": "1906328", 
    "regionName": "Geyserville"
  }, 
  {
    "currentEtor": "1508696100", 
    "hazardFlag": "1", 
    "lastUpdateTime": "1508684813", 
    "autoEtor": "1508696100", 
    "estCustAffected": "1", 
    "crewCurrentStatus": "PG&E has assigned a crew to assess the outage.", 
    "longitude": "-121.55866", 
    "latitude": "37.02556", 
    "outageStartTime": "1508684808", 
    "cause": "Unknown - PG&E will be assessing the cause.", 
    "outageNumber": "1907128", 
    "regionName": "Gilroy"
  }, 
  {
    "hazardFlag": "0", 
    "lastUpdateTime": "1508688247", 
    "estCustAffected": "1", 
    "crewCurrentStatus": "PG&E has assigned a crew to assess the outage.", 
    "longitude": "-122.48707", 
    "latitude": "38.3442", 
    "outageStartTime": "1508385000", 
    "cause": "Unknown - PG&E is investigating the cause.", 
    "outageNumber": "1907126", 
    "regionName": "Glen Ellen"
  }, 
  {
    "currentEtor": "1508731200", 
    "outageDevices": [
      {
        "latitude": "38.41219", 
        "longitude": "-122.50713"
      }, 
      {
        "latitude": "38.41492", 
        "longitude": "-122.50675"
      }, 
      {
        "latitude": "38.41391", 
        "longitude": "-122.50714"
      }
    ], 
    "hazardFlag": "0", 
    "lastUpdateTime": "1508636293", 
    "estCustAffected": "4", 
    "crewCurrentStatus": "PG&E repair crew is on-site working to restore power.", 
    "longitude": "-122.5098", 
    "latitude": "38.41215", 
    "outageStartTime": "1507527070", 
    "cause": "Found a damaged power pole in the area.", 
    "outageNumber": "1901439", 
    "regionName": "Glen Ellen"
  }, 
  {
    "currentEtor": "1508731200", 
    "outageDevices": [
      {
        "latitude": "38.36739", 
        "longitude": "-122.46494"
      }, 
      {
        "latitude": "38.37145", 
        "longitude": "-122.45821"
      }, 
      {
        "latitude": "38.37548", 
        "longitude": "-122.45172"
      }, 
      {
        "latitude": "38.38126", 
        "longitude": "-122.45512"
      }, 
      {
        "latitude": "38.4001", 
        "longitude": "-122.47114"
      }, 
      {
        "latitude": "38.40028", 
        "longitude": "-122.47342"
      }, 
      {
        "latitude": "38.3971", 
        "longitude": "-122.48338"
      }, 
      {
        "latitude": "38.39255", 
        "longitude": "-122.49328"
      }, 
      {
        "latitude": "38.38812", 
        "longitude": "-122.49619"
      }, 
      {
        "latitude": "38.3846", 
        "longitude": "-122.49315"
      }, 
      {
        "latitude": "38.37222", 
        "longitude": "-122.47698"
      }
    ], 
    "hazardFlag": "3", 
    "lastUpdateTime": "1508635256", 
    "estCustAffected": "118", 
    "crewCurrentStatus": "PG&E repair crew is on-site working to restore power.", 
    "longitude": "-122.49641", 
    "latitude": "38.38712", 
    "outageStartTime": "1507531822", 
    "cause": "Found damaged equipment on a power pole.", 
    "outageNumber": "1903600", 
    "regionName": "Glen Ellen"
  }, 
  {
    "currentEtor": "1508720400", 
    "hazardFlag": "0", 
    "lastUpdateTime": "1508687522", 
    "estCustAffected": "2", 
    "crewCurrentStatus": "PG&E repair crew is on-site working to restore power.", 
    "longitude": "-122.51511", 
    "latitude": "38.39687", 
    "outageStartTime": "1507527070", 
    "cause": "Found a broken power pole in the area", 
    "outageNumber": "1903370", 
    "regionName": "Glen Ellen"
  }, 
  {
    "outageDevices": [
      {
        "latitude": "38.5849", 
        "longitude": "-122.68197"
      }, 
      {
        "latitude": "38.58632", 
        "longitude": "-122.68191"
      }, 
      {
        "latitude": "38.58711", 
        "longitude": "-122.6819"
      }, 
      {
        "latitude": "38.58814", 
        "longitude": "-122.68205"
      }
    ], 
    "hazardFlag": "0", 
    "lastUpdateTime": "1508655844", 
    "estCustAffected": "5", 
    "crewCurrentStatus": "PG&E has assigned a crew to assess the outage.", 
    "longitude": "-122.68196", 
    "latitude": "38.58434", 
    "outageStartTime": "1507530195", 
    "cause": "Unplanned emergency repairs.", 
    "outageNumber": "1906844", 
    "regionName": "Healdsburg"
  }, 
  {
    "currentEtor": "1508734800", 
    "outageDevices": [
      {
        "latitude": "38.41552", 
        "longitude": "-122.51219"
      }, 
      {
        "latitude": "38.42209", 
        "longitude": "-122.50643"
      }, 
      {
        "latitude": "38.43392", 
        "longitude": "-122.50519"
      }, 
      {
        "latitude": "38.4369", 
        "longitude": "-122.50888"
      }, 
      {
        "latitude": "38.43722", 
        "longitude": "-122.51291"
      }, 
      {
        "latitude": "38.4373", 
        "longitude": "-122.51617"
      }, 
      {
        "latitude": "38.42372", 
        "longitude": "-122.51878"
      }, 
      {
        "latitude": "38.42105", 
        "longitude": "-122.51665"
      }
    ], 
    "hazardFlag": "1", 
    "lastUpdateTime": "1508673924", 
    "estCustAffected": "20", 
    "crewCurrentStatus": "PG&E repair crew is on-site working to restore power.", 
    "longitude": "-122.51221", 
    "latitude": "38.41547", 
    "outageStartTime": "1507527070", 
    "cause": "Fire in the area.", 
    "outageNumber": "1901448", 
    "regionName": "Kenwood"
  }, 
  {
    "currentEtor": "1508731200", 
    "outageDevices": [
      {
        "latitude": "38.42821", 
        "longitude": "-122.54608"
      }, 
      {
        "latitude": "38.42852", 
        "longitude": "-122.54541"
      }, 
      {
        "latitude": "38.42846", 
        "longitude": "-122.54802"
      }
    ], 
    "hazardFlag": "1", 
    "lastUpdateTime": "1508635696", 
    "estCustAffected": "10", 
    "crewCurrentStatus": "PG&E repair crew is on-site working to restore power.", 
    "longitude": "-122.54998", 
    "latitude": "38.42826", 
    "outageStartTime": "1507524875", 
    "cause": "Fire in the area.", 
    "outageNumber": "1897214", 
    "regionName": "Kenwood"
  }, 
  {
    "currentEtor": "1508731200", 
    "outageDevices": [
      {
        "latitude": "38.42439", 
        "longitude": "-122.55351"
      }, 
      {
        "latitude": "38.42462", 
        "longitude": "-122.55318"
      }, 
      {
        "latitude": "38.42856", 
        "longitude": "-122.54991"
      }, 
      {
        "latitude": "38.42948", 
        "longitude": "-122.55067"
      }
    ], 
    "hazardFlag": "1", 
    "lastUpdateTime": "1508635753", 
    "estCustAffected": "7", 
    "crewCurrentStatus": "PG&E is sending a repair crew to the outage location.", 
    "longitude": "-122.55395", 
    "latitude": "38.42409", 
    "outageStartTime": "1507524875", 
    "cause": "Found a damaged power pole in the area.", 
    "outageNumber": "1894854", 
    "regionName": "Kenwood"
  }, 
  {
    "currentEtor": "1508734800", 
    "outageDevices": [
      {
        "latitude": "38.43572", 
        "longitude": "-122.54611"
      }, 
      {
        "latitude": "38.44937", 
        "longitude": "-122.5178"
      }, 
      {
        "latitude": "38.44461", 
        "longitude": "-122.53397"
      }
    ], 
    "hazardFlag": "0", 
    "lastUpdateTime": "1508686171", 
    "estCustAffected": "6", 
    "crewCurrentStatus": "PG&E repair crew is on-site working to restore power.", 
    "longitude": "-122.55371", 
    "latitude": "38.43151", 
    "outageStartTime": "1507524875", 
    "cause": "Found a broken power pole in the area", 
    "outageNumber": "1899921", 
    "regionName": "Kenwood"
  }, 
  {
    "currentEtor": "1508731200", 
    "outageDevices": [
      {
        "latitude": "38.42184", 
        "longitude": "-122.54512"
      }, 
      {
        "latitude": "38.42448", 
        "longitude": "-122.54226"
      }, 
      {
        "latitude": "38.42547", 
        "longitude": "-122.54171"
      }, 
      {
        "latitude": "38.42365", 
        "longitude": "-122.54575"
      }, 
      {
        "latitude": "38.42271", 
        "longitude": "-122.54586"
      }
    ], 
    "hazardFlag": "1", 
    "lastUpdateTime": "1508635300", 
    "estCustAffected": "8", 
    "crewCurrentStatus": "PG&E repair crew is on-site working to restore power.", 
    "longitude": "-122.54649", 
    "latitude": "38.42206", 
    "outageStartTime": "1507527070", 
    "cause": "Found a broken power pole in the area", 
    "outageNumber": "1900362", 
    "regionName": "Kenwood"
  }, 
  {
    "currentEtor": "1508713200", 
    "hazardFlag": "1", 
    "lastUpdateTime": "1508600176", 
    "estCustAffected": "2", 
    "crewCurrentStatus": "PG&E is sending a repair crew to the outage location.", 
    "longitude": "-122.57079", 
    "latitude": "38.3989", 
    "outageStartTime": "1508546400", 
    "cause": "Field personnel have found a downed power line.", 
    "outageNumber": "1906463", 
    "regionName": "Kenwood"
  }, 
  {
    "hazardFlag": "0", 
    "lastUpdateTime": "1508680283", 
    "estCustAffected": "1", 
    "crewCurrentStatus": "PG&E is sending a repair crew to the outage location.", 
    "longitude": "-122.55944", 
    "latitude": "38.42729", 
    "outageStartTime": "1508597520", 
    "cause": "There is a problem with the transformer.", 
    "outageNumber": "1906661", 
    "regionName": "Kenwood"
  }, 
  {
    "outageDevices": [
      {
        "latitude": "38.51197", 
        "longitude": "-122.71962"
      }, 
      {
        "latitude": "38.51321", 
        "longitude": "-122.71822"
      }, 
      {
        "latitude": "38.51447", 
        "longitude": "-122.71821"
      }, 
      {
        "latitude": "38.52284", 
        "longitude": "-122.71853"
      }, 
      {
        "latitude": "38.52426", 
        "longitude": "-122.71927"
      }
    ], 
    "hazardFlag": "0", 
    "lastUpdateTime": "1508685969", 
    "estCustAffected": "18", 
    "crewCurrentStatus": "PG&E is assessing the cause at the outage location.", 
    "longitude": "-122.71961", 
    "latitude": "38.5119", 
    "outageStartTime": "1508656020", 
    "cause": "Unknown - PG&E is investigating the cause.", 
    "outageNumber": "1907086", 
    "regionName": "Larkfield-Wikiup"
  }, 
  {
    "currentEtor": "1508696100", 
    "hazardFlag": "0", 
    "lastUpdateTime": "1508686506", 
    "autoEtor": "1508696100", 
    "estCustAffected": "1", 
    "crewCurrentStatus": "PG&E has assigned a crew to assess the outage.", 
    "longitude": "-122.11826", 
    "latitude": "37.39761", 
    "outageStartTime": "1508686498", 
    "cause": "Unknown - PG&E will be assessing the cause.", 
    "outageNumber": "1907133", 
    "regionName": "Los Altos"
  }, 
  {
    "outageDevices": [
      {
        "latitude": "36.54034", 
        "longitude": "-120.49382"
      }, 
      {
        "latitude": "36.54538", 
        "longitude": "-120.47965"
      }, 
      {
        "latitude": "36.54556", 
        "longitude": "-120.4842"
      }, 
      {
        "latitude": "36.54543", 
        "longitude": "-120.48797"
      }
    ], 
    "hazardFlag": "0", 
    "lastUpdateTime": "1508676223", 
    "estCustAffected": "4", 
    "crewCurrentStatus": "PG&E repair crew is en route to the outage location.", 
    "longitude": "-120.47866", 
    "latitude": "36.58797", 
    "outageStartTime": "1508663845", 
    "cause": "Field personnel have found a downed power line.", 
    "outageNumber": "1907099", 
    "regionName": "Mendota"
  }, 
  {
    "currentEtor": "1508710500", 
    "outageDevices": [
      {
        "latitude": "36.53089", 
        "longitude": "-120.48275"
      }, 
      {
        "latitude": "36.53322", 
        "longitude": "-120.47901"
      }, 
      {
        "latitude": "36.54538", 
        "longitude": "-120.47889"
      }, 
      {
        "latitude": "36.53092", 
        "longitude": "-120.48527"
      }
    ], 
    "hazardFlag": "0", 
    "lastUpdateTime": "1508680578", 
    "estCustAffected": "5", 
    "crewCurrentStatus": "PG&E repair crew is en route to the outage location.", 
    "longitude": "-120.4793", 
    "latitude": "36.54539", 
    "outageStartTime": "1508652240", 
    "cause": "Field personnel have found a downed power line.", 
    "outageNumber": "1907083", 
    "regionName": "Mendota"
  }, 
  {
    "currentEtor": "1508738400", 
    "outageDevices": [
      {
        "latitude": "38.34253", 
        "longitude": "-122.24627"
      }, 
      {
        "latitude": "38.34473", 
        "longitude": "-122.24357"
      }, 
      {
        "latitude": "38.34324", 
        "longitude": "-122.24626"
      }
    ], 
    "hazardFlag": "0", 
    "lastUpdateTime": "1508683060", 
    "estCustAffected": "10", 
    "crewCurrentStatus": "PG&E is unable to access the affected equipment.", 
    "longitude": "-122.24394", 
    "latitude": "38.3456", 
    "outageStartTime": "1508008993", 
    "cause": "Fire in the area.", 
    "outageNumber": "1901442", 
    "regionName": "Napa"
  }, 
  {
    "currentEtor": "1508738400", 
    "outageDevices": [
      {
        "latitude": "38.39407", 
        "longitude": "-122.32127"
      }, 
      {
        "latitude": "38.39788", 
        "longitude": "-122.31301"
      }, 
      {
        "latitude": "38.39972", 
        "longitude": "-122.31065"
      }
    ], 
    "hazardFlag": "0", 
    "lastUpdateTime": "1508524291", 
    "estCustAffected": "6", 
    "crewCurrentStatus": "PG&E repair crew is on-site working to restore power.", 
    "longitude": "-122.32136", 
    "latitude": "38.39402", 
    "outageStartTime": "1507531680", 
    "cause": "There is a problem with the transformer.", 
    "outageNumber": "1897805", 
    "regionName": "Napa"
  }, 
  {
    "currentEtor": "1508769000", 
    "hazardFlag": "0", 
    "longitude": "-122.48813", 
    "lastUpdateTime": "1508566152", 
    "crewEta": "1508430660", 
    "crewCurrentStatus": "PG&E repair crew is on-site working to restore power.", 
    "estCustAffected": "2", 
    "latitude": "38.42672", 
    "outageStartTime": "1507522920", 
    "cause": "Found a broken power pole in the area", 
    "outageNumber": "1903503", 
    "regionName": "Napa"
  }, 
  {
    "currentEtor": "1508979600", 
    "hazardFlag": "0", 
    "lastUpdateTime": "1508681786", 
    "estCustAffected": "2", 
    "crewCurrentStatus": "PG&E is sending a repair crew to the outage location.", 
    "longitude": "-122.24576", 
    "latitude": "38.44058", 
    "outageStartTime": "1507523520", 
    "cause": "Fire in the area.", 
    "outageNumber": "1901420", 
    "regionName": "Napa"
  }, 
  {
    "currentEtor": "1508738400", 
    "hazardFlag": "0", 
    "lastUpdateTime": "1508563389", 
    "estCustAffected": "1", 
    "crewCurrentStatus": "PG&E repair crew is on-site working to restore power.", 
    "longitude": "-122.37766", 
    "latitude": "38.33449", 
    "outageStartTime": "1507910631", 
    "cause": "Found a broken power pole in the area", 
    "outageNumber": "1903235", 
    "regionName": "Napa"
  }, 
  {
    "hazardFlag": "1", 
    "lastUpdateTime": "1508651192", 
    "estCustAffected": "1", 
    "crewCurrentStatus": "PG&E is sending a repair crew to the outage location.", 
    "longitude": "-122.28264", 
    "latitude": "38.37266", 
    "outageStartTime": "1508629584", 
    "cause": "Trees are in contact with electrical equipment.", 
    "outageNumber": "1906962", 
    "regionName": "Napa"
  }, 
  {
    "currentEtor": "1508738400", 
    "outageDevices": [
      {
        "latitude": "38.325", 
        "longitude": "-122.40161"
      }, 
      {
        "latitude": "38.33172", 
        "longitude": "-122.39989"
      }, 
      {
        "latitude": "38.33305", 
        "longitude": "-122.40125"
      }, 
      {
        "latitude": "38.33219", 
        "longitude": "-122.4078"
      }, 
      {
        "latitude": "38.33204", 
        "longitude": "-122.40796"
      }, 
      {
        "latitude": "38.32607", 
        "longitude": "-122.40329"
      }
    ], 
    "hazardFlag": "0", 
    "longitude": "-122.39251", 
    "lastUpdateTime": "1508519599", 
    "crewEta": "1508519580", 
    "crewCurrentStatus": "PG&E repair crew is on-site working to restore power.", 
    "estCustAffected": "14", 
    "latitude": "38.3394", 
    "outageStartTime": "1507910631", 
    "cause": "Unplanned emergency repairs.", 
    "outageNumber": "1904404", 
    "regionName": "Napa"
  }, 
  {
    "currentEtor": "1508785200", 
    "hazardFlag": "0", 
    "lastUpdateTime": "1508629184", 
    "estCustAffected": "2", 
    "crewCurrentStatus": "PG&E repair crew is on-site working to restore power.", 
    "longitude": "-122.36753", 
    "latitude": "38.30355", 
    "outageStartTime": "1508536403", 
    "cause": "Fire in the area.", 
    "outageNumber": "1906377", 
    "regionName": "Napa"
  }, 
  {
    "currentEtor": "1508741940", 
    "outageDevices": [
      {
        "latitude": "38.34074", 
        "longitude": "-122.41004"
      }, 
      {
        "latitude": "38.34257", 
        "longitude": "-122.40294"
      }, 
      {
        "latitude": "38.34548", 
        "longitude": "-122.39978"
      }, 
      {
        "latitude": "38.35287", 
        "longitude": "-122.42523"
      }, 
      {
        "latitude": "38.34849", 
        "longitude": "-122.42481"
      }, 
      {
        "latitude": "38.34776", 
        "longitude": "-122.42434"
      }
    ], 
    "hazardFlag": "2", 
    "lastUpdateTime": "1508423390", 
    "estCustAffected": "29", 
    "crewCurrentStatus": "PG&E repair crew is on-site working to restore power.", 
    "longitude": "-122.39906", 
    "latitude": "38.34543", 
    "outageStartTime": "1507526741", 
    "cause": "Field personnel have found a downed power line.", 
    "outageNumber": "1894077", 
    "regionName": "Napa"
  }, 
  {
    "hazardFlag": "0", 
    "lastUpdateTime": "1508688368", 
    "estCustAffected": "1", 
    "crewCurrentStatus": "PG&E has assigned a crew to assess the outage.", 
    "longitude": "-122.24971", 
    "latitude": "38.37712", 
    "outageStartTime": "1508688357", 
    "cause": "Unknown - PG&E will be assessing the cause.", 
    "outageNumber": "1907142", 
    "regionName": "Napa"
  }, 
  {
    "hazardFlag": "0", 
    "longitude": "-122.23391", 
    "lastUpdateTime": "1508659010", 
    "estCustAffected": "1", 
    "crewCurrentStatus": "PG&E assessment crew is en route to the outage.", 
    "crewEta": "1508690460", 
    "latitude": "38.35201", 
    "outageStartTime": "1508637360", 
    "cause": "Unknown - PG&E is investigating the cause.", 
    "outageNumber": "1907037", 
    "regionName": "Napa"
  }, 
  {
    "currentEtor": "1508769000", 
    "hazardFlag": "1", 
    "lastUpdateTime": "1508566151", 
    "estCustAffected": "2", 
    "crewCurrentStatus": "PG&E repair crew is on-site working to restore power.", 
    "longitude": "-122.32812", 
    "latitude": "38.40222", 
    "outageStartTime": "1507531680", 
    "cause": "Found a broken power pole in the area", 
    "outageNumber": "1897775", 
    "regionName": "Napa"
  }, 
  {
    "currentEtor": "1508741940", 
    "outageDevices": [
      {
        "latitude": "38.3825", 
        "longitude": "-122.4455"
      }, 
      {
        "latitude": "38.38304", 
        "longitude": "-122.44307"
      }, 
      {
        "latitude": "38.38729", 
        "longitude": "-122.42912"
      }, 
      {
        "latitude": "38.38993", 
        "longitude": "-122.43064"
      }, 
      {
        "latitude": "38.40074", 
        "longitude": "-122.43844"
      }, 
      {
        "latitude": "38.3985", 
        "longitude": "-122.46616"
      }, 
      {
        "latitude": "38.39258", 
        "longitude": "-122.45974"
      }, 
      {
        "latitude": "38.38519", 
        "longitude": "-122.44946"
      }
    ], 
    "hazardFlag": "2", 
    "lastUpdateTime": "1508514897", 
    "estCustAffected": "43", 
    "crewCurrentStatus": "PG&E repair crew is on-site working to restore power.", 
    "longitude": "-122.43216", 
    "latitude": "38.38679", 
    "outageStartTime": "1507707951", 
    "cause": "Fire in the area.", 
    "outageNumber": "1899634", 
    "regionName": "Napa"
  }, 
  {
    "hazardFlag": "0", 
    "lastUpdateTime": "1508688061", 
    "estCustAffected": "3", 
    "crewCurrentStatus": "PG&E is unable to access the affected equipment.", 
    "longitude": "-122.2956", 
    "latitude": "38.40504", 
    "outageStartTime": "1508623178", 
    "cause": "Unknown - PG&E will be assessing the cause.", 
    "outageNumber": "1906904", 
    "regionName": "Napa"
  }, 
  {
    "currentEtor": "1508716800", 
    "hazardFlag": "0", 
    "lastUpdateTime": "1508636307", 
    "estCustAffected": "1", 
    "crewCurrentStatus": "PG&E repair crew is on-site working to restore power.", 
    "longitude": "-122.36182", 
    "latitude": "38.31094", 
    "outageStartTime": "1508621781", 
    "cause": "Found damage to underground equipment.", 
    "outageNumber": "1906872", 
    "regionName": "Napa"
  }, 
  {
    "currentEtor": "1508742060", 
    "outageDevices": [
      {
        "latitude": "38.36592", 
        "longitude": "-122.39372"
      }, 
      {
        "latitude": "38.3667", 
        "longitude": "-122.38959"
      }, 
      {
        "latitude": "38.37265", 
        "longitude": "-122.38722"
      }, 
      {
        "latitude": "38.37413", 
        "longitude": "-122.38932"
      }, 
      {
        "latitude": "38.36612", 
        "longitude": "-122.3989"
      }
    ], 
    "hazardFlag": "0", 
    "lastUpdateTime": "1508569303", 
    "estCustAffected": "8", 
    "crewCurrentStatus": "PG&E repair crew is on-site working to restore power.", 
    "longitude": "-122.38855", 
    "latitude": "38.37498", 
    "outageStartTime": "1507531680", 
    "cause": "Fire in the area.", 
    "outageNumber": "1902721", 
    "regionName": "Napa"
  }, 
  {
    "currentEtor": "1508979600", 
    "outageDevices": [
      {
        "latitude": "38.4299", 
        "longitude": "-122.2471"
      }, 
      {
        "latitude": "38.43079", 
        "longitude": "-122.24339"
      }, 
      {
        "latitude": "38.43708", 
        "longitude": "-122.24324"
      }, 
      {
        "latitude": "38.4442", 
        "longitude": "-122.24583"
      }, 
      {
        "latitude": "38.44748", 
        "longitude": "-122.25119"
      }, 
      {
        "latitude": "38.44884", 
        "longitude": "-122.25473"
      }, 
      {
        "latitude": "38.45258", 
        "longitude": "-122.26845"
      }
    ], 
    "hazardFlag": "1", 
    "lastUpdateTime": "1508551290", 
    "estCustAffected": "25", 
    "crewCurrentStatus": "PG&E is sending a repair crew to the outage location.", 
    "longitude": "-122.24787", 
    "latitude": "38.42955", 
    "outageStartTime": "1507523520", 
    "cause": "Unplanned emergency repairs.", 
    "outageNumber": "1901273", 
    "regionName": "Napa"
  }, 
  {
    "currentEtor": "1508738400", 
    "hazardFlag": "0", 
    "lastUpdateTime": "1508637870", 
    "estCustAffected": "1", 
    "crewCurrentStatus": "PG&E repair crew is on-site working to restore power.", 
    "longitude": "-122.24726", 
    "latitude": "38.33419", 
    "outageStartTime": "1508281001", 
    "cause": "Found damage to an underground power cable.", 
    "outageNumber": "1902821", 
    "regionName": "Napa"
  }, 
  {
    "currentEtor": "1508731200", 
    "hazardFlag": "0", 
    "lastUpdateTime": "1508679066", 
    "estCustAffected": "1", 
    "crewCurrentStatus": "PG&E repair crew is on-site working to restore power.", 
    "longitude": "-122.39787", 
    "latitude": "38.29943", 
    "outageStartTime": "1507538827", 
    "cause": "Found a broken power pole in the area", 
    "outageNumber": "1902020", 
    "regionName": "Napa"
  }, 
  {
    "currentEtor": "1508731200", 
    "hazardFlag": "0", 
    "lastUpdateTime": "1508445452", 
    "estCustAffected": "1", 
    "crewCurrentStatus": "PG&E repair crew is on-site working to restore power.", 
    "longitude": "-122.39293", 
    "latitude": "38.29258", 
    "outageStartTime": "1507538827", 
    "cause": "Found a broken power pole in the area", 
    "outageNumber": "1902022", 
    "regionName": "Napa"
  }, 
  {
    "currentEtor": "1508731200", 
    "hazardFlag": "1", 
    "lastUpdateTime": "1508630265", 
    "estCustAffected": "2", 
    "crewCurrentStatus": "PG&E repair crew is on-site working to restore power.", 
    "longitude": "-122.39403", 
    "latitude": "38.28737", 
    "outageStartTime": "1507538827", 
    "cause": "Found a broken power pole in the area", 
    "outageNumber": "1902028", 
    "regionName": "Napa"
  }, 
  {
    "currentEtor": "1508979600", 
    "outageDevices": [
      {
        "latitude": "38.40944", 
        "longitude": "-122.24589"
      }, 
      {
        "latitude": "38.42668", 
        "longitude": "-122.24724"
      }, 
      {
        "latitude": "38.4275", 
        "longitude": "-122.24744"
      }, 
      {
        "latitude": "38.43014", 
        "longitude": "-122.24814"
      }, 
      {
        "latitude": "38.41817", 
        "longitude": "-122.26065"
      }
    ], 
    "hazardFlag": "1", 
    "lastUpdateTime": "1508681858", 
    "estCustAffected": "10", 
    "crewCurrentStatus": "PG&E is sending a repair crew to the outage location.", 
    "longitude": "-122.24451", 
    "latitude": "38.40763", 
    "outageStartTime": "1507523520", 
    "cause": "Unplanned emergency repairs.", 
    "outageNumber": "1906414", 
    "regionName": "Napa"
  }, 
  {
    "currentEtor": "1508769000", 
    "hazardFlag": "0", 
    "lastUpdateTime": "1508566151", 
    "estCustAffected": "2", 
    "crewCurrentStatus": "PG&E repair crew is on-site working to restore power.", 
    "longitude": "-122.40697", 
    "latitude": "38.36556", 
    "outageStartTime": "1507741800", 
    "cause": "Fire in the area.", 
    "outageNumber": "1898325", 
    "regionName": "Napa"
  }, 
  {
    "hazardFlag": "0", 
    "lastUpdateTime": "1508622525", 
    "estCustAffected": "1", 
    "crewCurrentStatus": "PG&E is sending a repair crew to the outage location.", 
    "longitude": "-122.29627", 
    "latitude": "38.37281", 
    "outageStartTime": "1508536553", 
    "cause": "Found damage to an underground power cable.", 
    "outageNumber": "1906278", 
    "regionName": "Napa"
  }, 
  {
    "outageDevices": [
      {
        "latitude": "38.42431", 
        "longitude": "-122.49303"
      }, 
      {
        "latitude": "38.42447", 
        "longitude": "-122.48981"
      }, 
      {
        "latitude": "38.42577", 
        "longitude": "-122.48794"
      }, 
      {
        "latitude": "38.4308", 
        "longitude": "-122.48755"
      }, 
      {
        "latitude": "38.43559", 
        "longitude": "-122.48832"
      }, 
      {
        "latitude": "38.42873", 
        "longitude": "-122.50058"
      }, 
      {
        "latitude": "38.42799", 
        "longitude": "-122.5015"
      }
    ], 
    "hazardFlag": "0", 
    "lastUpdateTime": "1508676101", 
    "estCustAffected": "22", 
    "crewCurrentStatus": "PG&E is assessing the cause at the outage location.", 
    "longitude": "-122.49003", 
    "latitude": "38.42425", 
    "outageStartTime": "1507522920", 
    "cause": "Unknown - PG&E is investigating the cause.", 
    "outageNumber": "1906993", 
    "regionName": "Napa"
  }, 
  {
    "currentEtor": "1508738400", 
    "outageDevices": [
      {
        "latitude": "38.36182", 
        "longitude": "-122.41652"
      }, 
      {
        "latitude": "38.36553", 
        "longitude": "-122.4102"
      }, 
      {
        "latitude": "38.36696", 
        "longitude": "-122.4093"
      }, 
      {
        "latitude": "38.36981", 
        "longitude": "-122.40943"
      }, 
      {
        "latitude": "38.37513", 
        "longitude": "-122.41196"
      }, 
      {
        "latitude": "38.3835", 
        "longitude": "-122.42417"
      }, 
      {
        "latitude": "38.38607", 
        "longitude": "-122.43011"
      }, 
      {
        "latitude": "38.38618", 
        "longitude": "-122.43234"
      }, 
      {
        "latitude": "38.38391", 
        "longitude": "-122.43387"
      }, 
      {
        "latitude": "38.3814", 
        "longitude": "-122.43312"
      }, 
      {
        "latitude": "38.37684", 
        "longitude": "-122.43037"
      }, 
      {
        "latitude": "38.36446", 
        "longitude": "-122.42256"
      }
    ], 
    "hazardFlag": "1", 
    "lastUpdateTime": "1508611995", 
    "estCustAffected": "81", 
    "crewCurrentStatus": "PG&E repair crew is on-site working to restore power.", 
    "longitude": "-122.40879", 
    "latitude": "38.36677", 
    "outageStartTime": "1507707951", 
    "cause": "Field personnel have found a downed power line.", 
    "outageNumber": "1898220", 
    "regionName": "Napa"
  }, 
  {
    "currentEtor": "1508769000", 
    "hazardFlag": "0", 
    "lastUpdateTime": "1508566150", 
    "estCustAffected": "2", 
    "crewCurrentStatus": "PG&E repair crew is on-site working to restore power.", 
    "longitude": "-122.3454", 
    "latitude": "38.40083", 
    "outageStartTime": "1507531680", 
    "cause": "Fire in the area.", 
    "outageNumber": "1897734", 
    "regionName": "Napa"
  }, 
  {
    "currentEtor": "1508741940", 
    "hazardFlag": "0", 
    "lastUpdateTime": "1508657032", 
    "estCustAffected": "2", 
    "crewCurrentStatus": "PG&E repair crew is on-site working to restore power.", 
    "longitude": "-122.28005", 
    "latitude": "38.37244", 
    "outageStartTime": "1507526400", 
    "cause": "Fire in the area.", 
    "outageNumber": "1901667", 
    "regionName": "Napa"
  }, 
  {
    "currentEtor": "1508741940", 
    "outageDevices": [
      {
        "latitude": "38.36709", 
        "longitude": "-122.42516"
      }, 
      {
        "latitude": "38.37055", 
        "longitude": "-122.41838"
      }, 
      {
        "latitude": "38.37223", 
        "longitude": "-122.41879"
      }, 
      {
        "latitude": "38.37384", 
        "longitude": "-122.43212"
      }, 
      {
        "latitude": "38.37273", 
        "longitude": "-122.43214"
      }, 
      {
        "latitude": "38.36831", 
        "longitude": "-122.42973"
      }
    ], 
    "hazardFlag": "0", 
    "lastUpdateTime": "1508546368", 
    "estCustAffected": "29", 
    "crewCurrentStatus": "PG&E repair crew is on-site working to restore power.", 
    "longitude": "-122.41703", 
    "latitude": "38.37265", 
    "outageStartTime": "1507707951", 
    "cause": "Fire in the area.", 
    "outageNumber": "1901453", 
    "regionName": "Napa"
  }, 
  {
    "hazardFlag": "0", 
    "lastUpdateTime": "1508549484", 
    "estCustAffected": "1", 
    "crewCurrentStatus": "PG&E is sending a repair crew to the outage location.", 
    "longitude": "-122.25038", 
    "latitude": "38.34193", 
    "outageStartTime": "1508535863", 
    "cause": "There is a problem with the transformer.", 
    "outageNumber": "1906267", 
    "regionName": "Napa"
  }, 
  {
    "currentEtor": "1508769000", 
    "hazardFlag": "0", 
    "lastUpdateTime": "1508603079", 
    "estCustAffected": "1", 
    "crewCurrentStatus": "PG&E repair crew is on-site working to restore power.", 
    "longitude": "-122.26777", 
    "latitude": "38.36409", 
    "outageStartTime": "1507526400", 
    "cause": "Fire in the area.", 
    "outageNumber": "1901660", 
    "regionName": "Napa"
  }, 
  {
    "currentEtor": "1508692500", 
    "outageDevices": [
      {
        "latitude": "35.04818", 
        "longitude": "-120.46999"
      }, 
      {
        "latitude": "35.05119", 
        "longitude": "-120.46663"
      }, 
      {
        "latitude": "35.05238", 
        "longitude": "-120.46554"
      }, 
      {
        "latitude": "35.05426", 
        "longitude": "-120.46793"
      }, 
      {
        "latitude": "35.05476", 
        "longitude": "-120.47032"
      }, 
      {
        "latitude": "35.05109", 
        "longitude": "-120.47395"
      }, 
      {
        "latitude": "35.0501", 
        "longitude": "-120.47443"
      }, 
      {
        "latitude": "35.04948", 
        "longitude": "-120.47375"
      }, 
      {
        "latitude": "35.04834", 
        "longitude": "-120.4712"
      }
    ], 
    "hazardFlag": "0", 
    "longitude": "-120.47284", 
    "lastUpdateTime": "1508687909", 
    "autoEtor": "1508692500", 
    "crewEta": "1508684340", 
    "crewCurrentStatus": "PG&E is assessing the cause at the outage location.", 
    "estCustAffected": "16", 
    "latitude": "35.04811", 
    "outageStartTime": "1508681139", 
    "cause": "Unknown - PG&E is investigating the cause.", 
    "outageNumber": "1907115", 
    "regionName": "Nipomo"
  }, 
  {
    "hazardFlag": "0", 
    "lastUpdateTime": "1508687540", 
    "estCustAffected": "1", 
    "crewCurrentStatus": "PG&E assessment crew is en route to the outage.", 
    "longitude": "-122.19769", 
    "latitude": "37.83343", 
    "outageStartTime": "1508687530", 
    "cause": "Unknown - PG&E will be assessing the cause.", 
    "outageNumber": "1907138", 
    "regionName": "Oakland"
  }, 
  {
    "hazardFlag": "2", 
    "lastUpdateTime": "1508256315", 
    "estCustAffected": "3", 
    "crewCurrentStatus": "PG&E is sending a repair crew to the outage location.", 
    "longitude": "-122.96688", 
    "latitude": "38.37673", 
    "outageStartTime": "1508198985", 
    "cause": "Found a damaged power pole in the area.", 
    "outageNumber": "1902243", 
    "regionName": "Occidental"
  }, 
  {
    "currentEtor": "1508724000", 
    "hazardFlag": "0", 
    "lastUpdateTime": "1508637091", 
    "estCustAffected": "1", 
    "crewCurrentStatus": "PG&E is sending a repair crew to the outage location.", 
    "longitude": "-121.36579", 
    "latitude": "39.55263", 
    "outageStartTime": "1508621289", 
    "cause": "There is a problem with the transformer.", 
    "outageNumber": "1906865", 
    "regionName": "Oroville"
  }, 
  {
    "currentEtor": "1508803200", 
    "outageDevices": [
      {
        "latitude": "39.88815", 
        "longitude": "-121.37016"
      }, 
      {
        "latitude": "39.91177", 
        "longitude": "-121.32672"
      }, 
      {
        "latitude": "39.90882", 
        "longitude": "-121.33686"
      }, 
      {
        "latitude": "39.90571", 
        "longitude": "-121.34749"
      }, 
      {
        "latitude": "39.9002", 
        "longitude": "-121.35973"
      }
    ], 
    "hazardFlag": "0", 
    "lastUpdateTime": "1508598851", 
    "estCustAffected": "3", 
    "crewCurrentStatus": "PG&E is sending a repair crew to the outage location.", 
    "longitude": "-121.44946", 
    "latitude": "39.78392", 
    "outageStartTime": "1508523488", 
    "cause": "Found damaged equipment on a power pole.", 
    "outageNumber": "1905981", 
    "regionName": "Oroville"
  }, 
  {
    "currentEtor": "1508697900", 
    "hazardFlag": "0", 
    "longitude": "-121.93148", 
    "lastUpdateTime": "1508687984", 
    "autoEtor": "1508697900", 
    "crewEta": "1508691540", 
    "crewCurrentStatus": "PG&E assessment crew is en route to the outage.", 
    "estCustAffected": "1", 
    "latitude": "36.6043", 
    "outageStartTime": "1508687100", 
    "cause": "Unknown - PG&E will be assessing the cause.", 
    "outageNumber": "1907139", 
    "regionName": "Pacific Grove"
  }, 
  {
    "currentEtor": "1508700600", 
    "hazardFlag": "0", 
    "lastUpdateTime": "1508687959", 
    "autoEtor": "1508700600", 
    "estCustAffected": "1", 
    "crewCurrentStatus": "PG&E has assigned a crew to assess the outage.", 
    "longitude": "-120.57672", 
    "latitude": "35.57398", 
    "outageStartTime": "1508687951", 
    "cause": "Unknown - PG&E will be assessing the cause.", 
    "outageNumber": "1907140", 
    "regionName": "Paso Robles"
  }, 
  {
    "currentEtor": "1508693400", 
    "hazardFlag": "0", 
    "longitude": "-120.95145", 
    "lastUpdateTime": "1508685397", 
    "autoEtor": "1508693400", 
    "crewEta": "1508686200", 
    "crewCurrentStatus": "PG&E is assessing the cause at the outage location.", 
    "estCustAffected": "1", 
    "latitude": "38.70311", 
    "outageStartTime": "1508681580", 
    "cause": "Unknown - PG&E is investigating the cause.", 
    "outageNumber": "1907116", 
    "regionName": "Rescue"
  }, 
  {
    "currentEtor": "1508742060", 
    "hazardFlag": "0", 
    "lastUpdateTime": "1508569302", 
    "estCustAffected": "3", 
    "crewCurrentStatus": "PG&E is sending a repair crew to the outage location.", 
    "longitude": "-122.42466", 
    "latitude": "38.46091", 
    "outageStartTime": "1508024580", 
    "cause": "Field personnel have found a downed power line.", 
    "outageNumber": "1900999", 
    "regionName": "Rutherford"
  }, 
  {
    "currentEtor": "1508741940", 
    "hazardFlag": "0", 
    "lastUpdateTime": "1508682421", 
    "estCustAffected": "3", 
    "crewCurrentStatus": "PG&E repair crew is on-site working to restore power.", 
    "longitude": "-122.44974", 
    "latitude": "38.48748", 
    "outageStartTime": "1507525020", 
    "cause": "Fire in the area.", 
    "outageNumber": "1897493", 
    "regionName": "Saint Helena"
  }, 
  {
    "currentEtor": "1508914740", 
    "outageDevices": [
      {
        "latitude": "38.46351", 
        "longitude": "-122.48346"
      }, 
      {
        "latitude": "38.46401", 
        "longitude": "-122.46277"
      }, 
      {
        "latitude": "38.46631", 
        "longitude": "-122.46383"
      }, 
      {
        "latitude": "38.47155", 
        "longitude": "-122.47268"
      }, 
      {
        "latitude": "38.46937", 
        "longitude": "-122.48435"
      }
    ], 
    "hazardFlag": "1", 
    "lastUpdateTime": "1508624618", 
    "estCustAffected": "11", 
    "crewCurrentStatus": "PG&E is sending a repair crew to the outage location.", 
    "longitude": "-122.46242", 
    "latitude": "38.46391", 
    "outageStartTime": "1507971600", 
    "cause": "Fire in the area.", 
    "outageNumber": "1900520", 
    "regionName": "Saint Helena"
  }, 
  {
    "currentEtor": "1508713200", 
    "hazardFlag": "0", 
    "lastUpdateTime": "1508688249", 
    "estCustAffected": "2", 
    "crewCurrentStatus": "PG&E repair crew is en route to the outage location.", 
    "longitude": "-122.18346", 
    "latitude": "37.71029", 
    "outageStartTime": "1508672400", 
    "cause": "There is a problem with the transformer.", 
    "outageNumber": "1907105", 
    "regionName": "San Leandro"
  }, 
  {
    "currentEtor": "1508697900", 
    "hazardFlag": "1", 
    "lastUpdateTime": "1508685265", 
    "estCustAffected": "50", 
    "crewCurrentStatus": "PG&E repair crew is on-site working to restore power.", 
    "longitude": "-120.69316", 
    "latitude": "35.32028", 
    "outageStartTime": "1508678400", 
    "cause": "Field personnel have found a downed power line.", 
    "outageNumber": "1907112", 
    "regionName": "San Luis Obispo"
  }, 
  {
    "currentEtor": "1508702400", 
    "hazardFlag": "0", 
    "lastUpdateTime": "1508687398", 
    "autoEtor": "1508702400", 
    "estCustAffected": "1", 
    "crewCurrentStatus": "PG&E has assigned a crew to assess the outage.", 
    "longitude": "-120.43462", 
    "latitude": "34.97269", 
    "outageStartTime": "1508687397", 
    "cause": "Unknown - PG&E will be assessing the cause.", 
    "outageNumber": "1907136", 
    "regionName": "Santa Maria"
  }, 
  {
    "currentEtor": "1508727600", 
    "outageDevices": [
      {
        "latitude": "38.5124", 
        "longitude": "-122.67282"
      }, 
      {
        "latitude": "38.51664", 
        "longitude": "-122.66802"
      }, 
      {
        "latitude": "38.51792", 
        "longitude": "-122.6694"
      }, 
      {
        "latitude": "38.51564", 
        "longitude": "-122.67951"
      }, 
      {
        "latitude": "38.51301", 
        "longitude": "-122.67621"
      }, 
      {
        "latitude": "38.51256", 
        "longitude": "-122.6742"
      }
    ], 
    "hazardFlag": "0", 
    "lastUpdateTime": "1508635066", 
    "estCustAffected": "16", 
    "crewCurrentStatus": "PG&E repair crew is on-site working to restore power.", 
    "longitude": "-122.69075", 
    "latitude": "38.5111", 
    "outageStartTime": "1507538479", 
    "cause": "Found a broken power pole in the area", 
    "outageNumber": "1900828", 
    "regionName": "Santa Rosa"
  }, 
  {
    "currentEtor": "1508716800", 
    "outageDevices": [
      {
        "latitude": "38.55124", 
        "longitude": "-122.69379"
      }, 
      {
        "latitude": "38.55148", 
        "longitude": "-122.69214"
      }, 
      {
        "latitude": "38.55192", 
        "longitude": "-122.69069"
      }, 
      {
        "latitude": "38.55531", 
        "longitude": "-122.69009"
      }, 
      {
        "latitude": "38.55762", 
        "longitude": "-122.69219"
      }, 
      {
        "latitude": "38.55616", 
        "longitude": "-122.69567"
      }, 
      {
        "latitude": "38.55511", 
        "longitude": "-122.69674"
      }
    ], 
    "hazardFlag": "1", 
    "lastUpdateTime": "1508637365", 
    "estCustAffected": "14", 
    "crewCurrentStatus": "PG&E repair crew is on-site working to restore power.", 
    "longitude": "-122.69475", 
    "latitude": "38.55675", 
    "outageStartTime": "1508090477", 
    "cause": "Fire in the area.", 
    "outageNumber": "1902240", 
    "regionName": "Santa Rosa"
  }, 
  {
    "currentEtor": "1508734800", 
    "hazardFlag": "1", 
    "lastUpdateTime": "1508678990", 
    "estCustAffected": "5", 
    "crewCurrentStatus": "PG&E is sending a repair crew to the outage location.", 
    "longitude": "-122.72312", 
    "latitude": "38.47337", 
    "outageStartTime": "1507537718", 
    "cause": "Field personnel have found a downed power line.", 
    "outageNumber": "1899674", 
    "regionName": "Santa Rosa"
  }, 
  {
    "currentEtor": "1508727600", 
    "outageDevices": [
      {
        "latitude": "38.51147", 
        "longitude": "-122.72244"
      }, 
      {
        "latitude": "38.51217", 
        "longitude": "-122.72082"
      }, 
      {
        "latitude": "38.55272", 
        "longitude": "-122.67125"
      }, 
      {
        "latitude": "38.55798", 
        "longitude": "-122.67338"
      }, 
      {
        "latitude": "38.55914", 
        "longitude": "-122.67485"
      }, 
      {
        "latitude": "38.56159", 
        "longitude": "-122.67954"
      }, 
      {
        "latitude": "38.56615", 
        "longitude": "-122.73255"
      }, 
      {
        "latitude": "38.56186", 
        "longitude": "-122.73921"
      }, 
      {
        "latitude": "38.51167", 
        "longitude": "-122.72357"
      }
    ], 
    "hazardFlag": "1", 
    "lastUpdateTime": "1508688042", 
    "estCustAffected": "365", 
    "crewCurrentStatus": "PG&E repair crew is on-site working to restore power.", 
    "longitude": "-122.73548", 
    "latitude": "38.50307", 
    "outageStartTime": "1507532159", 
    "cause": "Fire in the area.", 
    "outageNumber": "1900114", 
    "regionName": "Santa Rosa"
  }, 
  {
    "currentEtor": "1508731200", 
    "hazardFlag": "0", 
    "lastUpdateTime": "1508635618", 
    "estCustAffected": "2", 
    "crewCurrentStatus": "PG&E repair crew is en route to the outage location.", 
    "longitude": "-122.68494", 
    "latitude": "38.49662", 
    "outageStartTime": "1507530660", 
    "cause": "Found a damaged power pole in the area.", 
    "outageNumber": "1901331", 
    "regionName": "Santa Rosa"
  }, 
  {
    "currentEtor": "1508731200", 
    "outageDevices": [
      {
        "latitude": "38.44339", 
        "longitude": "-122.5758"
      }, 
      {
        "latitude": "38.44415", 
        "longitude": "-122.57538"
      }, 
      {
        "latitude": "38.4448", 
        "longitude": "-122.57512"
      }, 
      {
        "latitude": "38.44819", 
        "longitude": "-122.57403"
      }, 
      {
        "latitude": "38.44924", 
        "longitude": "-122.57406"
      }, 
      {
        "latitude": "38.45327", 
        "longitude": "-122.57432"
      }, 
      {
        "latitude": "38.45593", 
        "longitude": "-122.57469"
      }, 
      {
        "latitude": "38.45941", 
        "longitude": "-122.58494"
      }, 
      {
        "latitude": "38.45749", 
        "longitude": "-122.58546"
      }
    ], 
    "hazardFlag": "0", 
    "lastUpdateTime": "1508674004", 
    "estCustAffected": "16", 
    "crewCurrentStatus": "PG&E repair crew is on-site working to restore power.", 
    "longitude": "-122.57604", 
    "latitude": "38.44275", 
    "outageStartTime": "1507935861", 
    "cause": "Found a damaged power pole in the area.", 
    "outageNumber": "1900315", 
    "regionName": "Santa Rosa"
  }, 
  {
    "currentEtor": "1508734800", 
    "outageDevices": [
      {
        "latitude": "38.50062", 
        "longitude": "-122.68624"
      }, 
      {
        "latitude": "38.50109", 
        "longitude": "-122.68534"
      }, 
      {
        "latitude": "38.50355", 
        "longitude": "-122.68123"
      }, 
      {
        "latitude": "38.50804", 
        "longitude": "-122.67865"
      }, 
      {
        "latitude": "38.50862", 
        "longitude": "-122.67961"
      }
    ], 
    "hazardFlag": "0", 
    "lastUpdateTime": "1508677946", 
    "estCustAffected": "8", 
    "crewCurrentStatus": "PG&E repair crew is on-site working to restore power.", 
    "longitude": "-122.68629", 
    "latitude": "38.50062", 
    "outageStartTime": "1507540260", 
    "cause": "Found a damaged power pole in the area.", 
    "outageNumber": "1901338", 
    "regionName": "Santa Rosa"
  }, 
  {
    "hazardFlag": "0", 
    "lastUpdateTime": "1508469453", 
    "estCustAffected": "4", 
    "crewCurrentStatus": "PG&E is sending a repair crew to the outage location.", 
    "longitude": "-122.64746", 
    "latitude": "38.36499", 
    "outageStartTime": "1508350924", 
    "cause": "Found a damaged power pole in the area.", 
    "outageNumber": "1903267", 
    "regionName": "Santa Rosa"
  }, 
  {
    "hazardFlag": "0", 
    "lastUpdateTime": "1508688210", 
    "estCustAffected": "1", 
    "crewCurrentStatus": "PG&E has assigned a crew to assess the outage.", 
    "longitude": "-122.74205", 
    "latitude": "38.48119", 
    "outageStartTime": "1508684022", 
    "cause": "Unknown - PG&E will be assessing the cause.", 
    "outageNumber": "1907122", 
    "regionName": "Santa Rosa"
  }, 
  {
    "hazardFlag": "0", 
    "lastUpdateTime": "1508443718", 
    "estCustAffected": "1", 
    "crewCurrentStatus": "PG&E is sending a repair crew to the outage location.", 
    "longitude": "-122.74024", 
    "latitude": "38.48116", 
    "outageStartTime": "1508431548", 
    "cause": "Found damage to an underground power cable.", 
    "outageNumber": "1903927", 
    "regionName": "Santa Rosa"
  }, 
  {
    "currentEtor": "1508727600", 
    "outageDevices": [
      {
        "latitude": "38.51101", 
        "longitude": "-122.71662"
      }, 
      {
        "latitude": "38.52367", 
        "longitude": "-122.69875"
      }, 
      {
        "latitude": "38.52683", 
        "longitude": "-122.69862"
      }, 
      {
        "latitude": "38.52907", 
        "longitude": "-122.70268"
      }, 
      {
        "latitude": "38.52608", 
        "longitude": "-122.71008"
      }, 
      {
        "latitude": "38.51946", 
        "longitude": "-122.71524"
      }, 
      {
        "latitude": "38.51578", 
        "longitude": "-122.7172"
      }, 
      {
        "latitude": "38.51254", 
        "longitude": "-122.71744"
      }, 
      {
        "latitude": "38.51194", 
        "longitude": "-122.71721"
      }
    ], 
    "hazardFlag": "1", 
    "lastUpdateTime": "1508634829", 
    "estCustAffected": "127", 
    "crewCurrentStatus": "PG&E repair crew is on-site working to restore power.", 
    "longitude": "-122.71642", 
    "latitude": "38.51092", 
    "outageStartTime": "1507527600", 
    "cause": "Found a broken power pole in the area", 
    "outageNumber": "1900806", 
    "regionName": "Santa Rosa"
  }, 
  {
    "currentEtor": "1508727600", 
    "outageDevices": [
      {
        "latitude": "38.54391", 
        "longitude": "-122.64461"
      }, 
      {
        "latitude": "38.54651", 
        "longitude": "-122.63645"
      }, 
      {
        "latitude": "38.5486", 
        "longitude": "-122.63102"
      }, 
      {
        "latitude": "38.55083", 
        "longitude": "-122.6509"
      }, 
      {
        "latitude": "38.5479", 
        "longitude": "-122.66704"
      }, 
      {
        "latitude": "38.54409", 
        "longitude": "-122.64843"
      }
    ], 
    "hazardFlag": "0", 
    "lastUpdateTime": "1508681340", 
    "estCustAffected": "43", 
    "crewCurrentStatus": "PG&E repair crew is on-site working to restore power.", 
    "longitude": "-122.66916", 
    "latitude": "38.54712", 
    "outageStartTime": "1507529829", 
    "cause": "Found a damaged power pole in the area.", 
    "outageNumber": "1900803", 
    "regionName": "Santa Rosa"
  }, 
  {
    "currentEtor": "1508731200", 
    "outageDevices": [
      {
        "latitude": "38.55124", 
        "longitude": "-122.65269"
      }, 
      {
        "latitude": "38.55152", 
        "longitude": "-122.6541"
      }, 
      {
        "latitude": "38.55172", 
        "longitude": "-122.65544"
      }
    ], 
    "hazardFlag": "0", 
    "lastUpdateTime": "1508678930", 
    "estCustAffected": "3", 
    "crewCurrentStatus": "PG&E repair crew is on-site working to restore power.", 
    "longitude": "-122.65125", 
    "latitude": "38.55051", 
    "outageStartTime": "1507529829", 
    "cause": "Found a damaged power pole in the area.", 
    "outageNumber": "1900801", 
    "regionName": "Santa Rosa"
  }, 
  {
    "currentEtor": "1508731200", 
    "outageDevices": [
      {
        "latitude": "38.55958", 
        "longitude": "-122.69188"
      }, 
      {
        "latitude": "38.56626", 
        "longitude": "-122.67559"
      }, 
      {
        "latitude": "38.57158", 
        "longitude": "-122.68004"
      }, 
      {
        "latitude": "38.57253", 
        "longitude": "-122.69441"
      }, 
      {
        "latitude": "38.56047", 
        "longitude": "-122.69375"
      }, 
      {
        "latitude": "38.5599", 
        "longitude": "-122.69354"
      }
    ], 
    "hazardFlag": "1", 
    "lastUpdateTime": "1508632715", 
    "estCustAffected": "33", 
    "crewCurrentStatus": "PG&E repair crew is on-site working to restore power.", 
    "longitude": "-122.6915", 
    "latitude": "38.55964", 
    "outageStartTime": "1507532159", 
    "cause": "Found a damaged power pole in the area.", 
    "outageNumber": "1904186", 
    "regionName": "Santa Rosa"
  }, 
  {
    "outageDevices": [
      {
        "latitude": "38.50645", 
        "longitude": "-122.70879"
      }, 
      {
        "latitude": "38.50746", 
        "longitude": "-122.7091"
      }, 
      {
        "latitude": "38.50834", 
        "longitude": "-122.70942"
      }, 
      {
        "latitude": "38.50901", 
        "longitude": "-122.70967"
      }
    ], 
    "hazardFlag": "0", 
    "lastUpdateTime": "1508623076", 
    "estCustAffected": "7", 
    "crewCurrentStatus": "PG&E has assigned a crew to assess the outage.", 
    "longitude": "-122.70963", 
    "latitude": "38.50905", 
    "outageStartTime": "1508611180", 
    "cause": "Found a broken power pole in the area", 
    "outageNumber": "1906774", 
    "regionName": "Santa Rosa"
  }, 
  {
    "currentEtor": "1508731200", 
    "hazardFlag": "0", 
    "lastUpdateTime": "1508636865", 
    "estCustAffected": "1", 
    "crewCurrentStatus": "PG&E repair crew is on-site working to restore power.", 
    "longitude": "-122.5735", 
    "latitude": "38.44764", 
    "outageStartTime": "1507524875", 
    "cause": "Field personnel have found a downed power line.", 
    "outageNumber": "1900167", 
    "regionName": "Santa Rosa"
  }, 
  {
    "currentEtor": "1508731200", 
    "hazardFlag": "0", 
    "lastUpdateTime": "1508678951", 
    "estCustAffected": "1", 
    "crewCurrentStatus": "PG&E repair crew is on-site working to restore power.", 
    "longitude": "-122.66194", 
    "latitude": "38.52521", 
    "outageStartTime": "1507529829", 
    "cause": "Found a broken power pole in the area", 
    "outageNumber": "1900887", 
    "regionName": "Santa Rosa"
  }, 
  {
    "currentEtor": "1508727600", 
    "outageDevices": [
      {
        "latitude": "38.51472", 
        "longitude": "-122.68695"
      }, 
      {
        "latitude": "38.51497", 
        "longitude": "-122.68603"
      }, 
      {
        "latitude": "38.51692", 
        "longitude": "-122.68368"
      }, 
      {
        "latitude": "38.52042", 
        "longitude": "-122.68362"
      }, 
      {
        "latitude": "38.52825", 
        "longitude": "-122.68986"
      }, 
      {
        "latitude": "38.52908", 
        "longitude": "-122.69225"
      }, 
      {
        "latitude": "38.52865", 
        "longitude": "-122.69277"
      }, 
      {
        "latitude": "38.51554", 
        "longitude": "-122.688"
      }
    ], 
    "hazardFlag": "0", 
    "lastUpdateTime": "1508635012", 
    "estCustAffected": "11", 
    "crewCurrentStatus": "PG&E repair crew is on-site working to restore power.", 
    "longitude": "-122.68601", 
    "latitude": "38.51313", 
    "outageStartTime": "1507523700", 
    "cause": "Found a broken power pole in the area", 
    "outageNumber": "1893956", 
    "regionName": "Santa Rosa"
  }, 
  {
    "currentEtor": "1508806800", 
    "outageDevices": [
      {
        "latitude": "38.50632", 
        "longitude": "-122.71655"
      }, 
      {
        "latitude": "38.50674", 
        "longitude": "-122.71327"
      }, 
      {
        "latitude": "38.50723", 
        "longitude": "-122.71238"
      }, 
      {
        "latitude": "38.50941", 
        "longitude": "-122.71707"
      }, 
      {
        "latitude": "38.50827", 
        "longitude": "-122.71786"
      }, 
      {
        "latitude": "38.50741", 
        "longitude": "-122.71835"
      }
    ], 
    "hazardFlag": "0", 
    "lastUpdateTime": "1508634526", 
    "estCustAffected": "20", 
    "crewCurrentStatus": "PG&E repair crew is on-site working to restore power.", 
    "longitude": "-122.71857", 
    "latitude": "38.50785", 
    "outageStartTime": "1508606926", 
    "cause": "Fire in the area.", 
    "outageNumber": "1906738", 
    "regionName": "Santa Rosa"
  }, 
  {
    "outageDevices": [
      {
        "latitude": "38.48128", 
        "longitude": "-122.73168"
      }, 
      {
        "latitude": "38.48213", 
        "longitude": "-122.73032"
      }, 
      {
        "latitude": "38.48189", 
        "longitude": "-122.73344"
      }, 
      {
        "latitude": "38.48169", 
        "longitude": "-122.73414"
      }
    ], 
    "hazardFlag": "1", 
    "lastUpdateTime": "1508586617", 
    "estCustAffected": "14", 
    "crewCurrentStatus": "PG&E is sending a repair crew to the outage location.", 
    "longitude": "-122.73419", 
    "latitude": "38.48167", 
    "outageStartTime": "1507532036", 
    "cause": "Found a broken power pole in the area", 
    "outageNumber": "1899150", 
    "regionName": "Santa Rosa"
  }, 
  {
    "hazardFlag": "0", 
    "lastUpdateTime": "1508625483", 
    "estCustAffected": "1", 
    "crewCurrentStatus": "PG&E is sending a repair crew to the outage location.", 
    "longitude": "-122.767", 
    "latitude": "38.42492", 
    "outageStartTime": "1508616641", 
    "cause": "There is a problem with the transformer.", 
    "outageNumber": "1906831", 
    "regionName": "Santa Rosa"
  }, 
  {
    "hazardFlag": "0", 
    "lastUpdateTime": "1508636596", 
    "estCustAffected": "2", 
    "crewCurrentStatus": "PG&E is sending a repair crew to the outage location.", 
    "longitude": "-122.72534", 
    "latitude": "38.50566", 
    "outageStartTime": "1508613720", 
    "cause": "Fire in the area.", 
    "outageNumber": "1906829", 
    "regionName": "Santa Rosa"
  }, 
  {
    "currentEtor": "1508731200", 
    "outageDevices": [
      {
        "latitude": "38.55117", 
        "longitude": "-122.66778"
      }, 
      {
        "latitude": "38.55326", 
        "longitude": "-122.66081"
      }, 
      {
        "latitude": "38.55339", 
        "longitude": "-122.66178"
      }, 
      {
        "latitude": "38.55213", 
        "longitude": "-122.66787"
      }
    ], 
    "hazardFlag": "0", 
    "lastUpdateTime": "1508678864", 
    "estCustAffected": "6", 
    "crewCurrentStatus": "PG&E repair crew is on-site working to restore power.", 
    "longitude": "-122.66777", 
    "latitude": "38.54988", 
    "outageStartTime": "1507529829", 
    "cause": "Found a damaged power pole in the area.", 
    "outageNumber": "1901028", 
    "regionName": "Santa Rosa"
  }, 
  {
    "currentEtor": "1508731200", 
    "outageDevices": [
      {
        "latitude": "38.50574", 
        "longitude": "-122.73402"
      }, 
      {
        "latitude": "38.50805", 
        "longitude": "-122.72783"
      }, 
      {
        "latitude": "38.51046", 
        "longitude": "-122.72479"
      }, 
      {
        "latitude": "38.5117", 
        "longitude": "-122.72441"
      }, 
      {
        "latitude": "38.51406", 
        "longitude": "-122.7275"
      }, 
      {
        "latitude": "38.51504", 
        "longitude": "-122.7304"
      }, 
      {
        "latitude": "38.50629", 
        "longitude": "-122.73496"
      }
    ], 
    "hazardFlag": "0", 
    "lastUpdateTime": "1508632734", 
    "estCustAffected": "32", 
    "crewCurrentStatus": "PG&E repair crew is on-site working to restore power.", 
    "longitude": "-122.72435", 
    "latitude": "38.51181", 
    "outageStartTime": "1507532159", 
    "cause": "Fire in the area.", 
    "outageNumber": "1905924", 
    "regionName": "Santa Rosa"
  }, 
  {
    "outageDevices": [
      {
        "latitude": "38.50013", 
        "longitude": "-122.71548"
      }, 
      {
        "latitude": "38.50192", 
        "longitude": "-122.71409"
      }, 
      {
        "latitude": "38.50377", 
        "longitude": "-122.7144"
      }, 
      {
        "latitude": "38.507", 
        "longitude": "-122.71949"
      }, 
      {
        "latitude": "38.50339", 
        "longitude": "-122.72431"
      }
    ], 
    "hazardFlag": "0", 
    "lastUpdateTime": "1508636580", 
    "estCustAffected": "24", 
    "crewCurrentStatus": "PG&E is sending a repair crew to the outage location.", 
    "longitude": "-122.72044", 
    "latitude": "38.50734", 
    "outageStartTime": "1508613660", 
    "cause": "Fire in the area.", 
    "outageNumber": "1906825", 
    "regionName": "Santa Rosa"
  }, 
  {
    "currentEtor": "1508734800", 
    "outageDevices": [
      {
        "latitude": "38.51716", 
        "longitude": "-122.67522"
      }, 
      {
        "latitude": "38.5209", 
        "longitude": "-122.67102"
      }, 
      {
        "latitude": "38.53302", 
        "longitude": "-122.67641"
      }, 
      {
        "latitude": "38.53386", 
        "longitude": "-122.68081"
      }, 
      {
        "latitude": "38.53293", 
        "longitude": "-122.68268"
      }, 
      {
        "latitude": "38.52675", 
        "longitude": "-122.68361"
      }, 
      {
        "latitude": "38.51901", 
        "longitude": "-122.6788"
      }, 
      {
        "latitude": "38.51724", 
        "longitude": "-122.67672"
      }
    ], 
    "hazardFlag": "0", 
    "lastUpdateTime": "1508641082", 
    "estCustAffected": "26", 
    "crewCurrentStatus": "PG&E repair crew is on-site working to restore power.", 
    "longitude": "-122.67969", 
    "latitude": "38.51685", 
    "outageStartTime": "1507538479", 
    "cause": "Fire in the area.", 
    "outageNumber": "1903332", 
    "regionName": "Santa Rosa"
  }, 
  {
    "currentEtor": "1508734800", 
    "outageDevices": [
      {
        "latitude": "38.51478", 
        "longitude": "-122.71893"
      }, 
      {
        "latitude": "38.51857", 
        "longitude": "-122.72029"
      }, 
      {
        "latitude": "38.51714", 
        "longitude": "-122.72056"
      }, 
      {
        "latitude": "38.5157", 
        "longitude": "-122.71989"
      }
    ], 
    "hazardFlag": "0", 
    "lastUpdateTime": "1508632766", 
    "estCustAffected": "14", 
    "crewCurrentStatus": "PG&E repair crew is on-site working to restore power.", 
    "longitude": "-122.7205", 
    "latitude": "38.51826", 
    "outageStartTime": "1507532159", 
    "cause": "Fire in the area.", 
    "outageNumber": "1899352", 
    "regionName": "Santa Rosa"
  }, 
  {
    "currentEtor": "1508719920", 
    "outageDevices": [
      {
        "latitude": "38.51209", 
        "longitude": "-122.7114"
      }, 
      {
        "latitude": "38.51299", 
        "longitude": "-122.71032"
      }, 
      {
        "latitude": "38.51728", 
        "longitude": "-122.70881"
      }, 
      {
        "latitude": "38.51817", 
        "longitude": "-122.70971"
      }, 
      {
        "latitude": "38.51864", 
        "longitude": "-122.71075"
      }, 
      {
        "latitude": "38.51839", 
        "longitude": "-122.71202"
      }, 
      {
        "latitude": "38.51654", 
        "longitude": "-122.71355"
      }, 
      {
        "latitude": "38.51444", 
        "longitude": "-122.71419"
      }
    ], 
    "hazardFlag": "0", 
    "lastUpdateTime": "1508688310", 
    "estCustAffected": "52", 
    "crewCurrentStatus": "PG&E repair crew is on-site working to restore power.", 
    "longitude": "-122.7114", 
    "latitude": "38.51136", 
    "outageStartTime": "1507527600", 
    "cause": "Found a damaged power pole in the area.", 
    "outageNumber": "1902478", 
    "regionName": "Santa Rosa"
  }, 
  {
    "hazardFlag": "1", 
    "lastUpdateTime": "1508570485", 
    "estCustAffected": "1", 
    "crewCurrentStatus": "PG&E is sending a repair crew to the outage location.", 
    "longitude": "-122.94105", 
    "latitude": "38.46471", 
    "outageStartTime": "1508548874", 
    "cause": "PG&E staff have found damage on the service line.", 
    "outageNumber": "1906480", 
    "regionName": "Sebastopol"
  }, 
  {
    "outageDevices": [
      {
        "latitude": "38.34592", 
        "longitude": "-122.45333"
      }, 
      {
        "latitude": "38.35015", 
        "longitude": "-122.44602"
      }, 
      {
        "latitude": "38.35951", 
        "longitude": "-122.44822"
      }
    ], 
    "hazardFlag": "0", 
    "lastUpdateTime": "1508686869", 
    "estCustAffected": "7", 
    "crewCurrentStatus": "PG&E is sending a repair crew to the outage location.", 
    "longitude": "-122.45377", 
    "latitude": "38.34586", 
    "outageStartTime": "1508368320", 
    "cause": "Fire in the area.", 
    "outageNumber": "1907130", 
    "regionName": "Sonoma"
  }, 
  {
    "currentEtor": "1508740740", 
    "outageDevices": [
      {
        "latitude": "38.2966", 
        "longitude": "-122.41196"
      }, 
      {
        "latitude": "38.29913", 
        "longitude": "-122.40667"
      }, 
      {
        "latitude": "38.30159", 
        "longitude": "-122.40362"
      }, 
      {
        "latitude": "38.30588", 
        "longitude": "-122.40309"
      }, 
      {
        "latitude": "38.31288", 
        "longitude": "-122.40752"
      }, 
      {
        "latitude": "38.31748", 
        "longitude": "-122.41066"
      }, 
      {
        "latitude": "38.3186", 
        "longitude": "-122.41867"
      }, 
      {
        "latitude": "38.31587", 
        "longitude": "-122.42089"
      }, 
      {
        "latitude": "38.30406", 
        "longitude": "-122.41677"
      }
    ], 
    "hazardFlag": "2", 
    "lastUpdateTime": "1508679003", 
    "estCustAffected": "52", 
    "crewCurrentStatus": "PG&E is sending a repair crew to the outage location.", 
    "longitude": "-122.41888", 
    "latitude": "38.28707", 
    "outageStartTime": "1507538827", 
    "cause": "Fire in the area.", 
    "outageNumber": "1900103", 
    "regionName": "Sonoma"
  }, 
  {
    "currentEtor": "1508734800", 
    "outageDevices": [
      {
        "latitude": "38.25258", 
        "longitude": "-122.39591"
      }, 
      {
        "latitude": "38.25279", 
        "longitude": "-122.39585"
      }, 
      {
        "latitude": "38.25404", 
        "longitude": "-122.40019"
      }, 
      {
        "latitude": "38.25265", 
        "longitude": "-122.40508"
      }
    ], 
    "hazardFlag": "1", 
    "lastUpdateTime": "1508678963", 
    "estCustAffected": "6", 
    "crewCurrentStatus": "PG&E is sending a repair crew to the outage location.", 
    "longitude": "-122.39592", 
    "latitude": "38.25256", 
    "outageStartTime": "1507540153", 
    "cause": "Fire in the area.", 
    "outageNumber": "1900231", 
    "regionName": "Sonoma"
  }, 
  {
    "outageDevices": [
      {
        "latitude": "38.20494", 
        "longitude": "-122.42742"
      }, 
      {
        "latitude": "38.20865", 
        "longitude": "-122.42628"
      }, 
      {
        "latitude": "38.2135", 
        "longitude": "-122.42564"
      }, 
      {
        "latitude": "38.22598", 
        "longitude": "-122.43439"
      }, 
      {
        "latitude": "38.2243", 
        "longitude": "-122.44447"
      }
    ], 
    "hazardFlag": "0", 
    "lastUpdateTime": "1508526683", 
    "estCustAffected": "10", 
    "crewCurrentStatus": "PG&E is sending a repair crew to the outage location.", 
    "longitude": "-122.45353", 
    "latitude": "38.23119", 
    "outageStartTime": "1508478993", 
    "cause": "Field personnel have found a downed power line.", 
    "outageNumber": "1904703", 
    "regionName": "Sonoma"
  }, 
  {
    "hazardFlag": "1", 
    "lastUpdateTime": "1508550686", 
    "estCustAffected": "1", 
    "crewCurrentStatus": "PG&E is sending a repair crew to the outage location.", 
    "longitude": "-122.41895", 
    "latitude": "38.28625", 
    "outageStartTime": "1508529078", 
    "cause": "Found a broken power pole in the area", 
    "outageNumber": "1906117", 
    "regionName": "Sonoma"
  }, 
  {
    "currentEtor": "1508731200", 
    "outageDevices": [
      {
        "latitude": "38.27617", 
        "longitude": "-122.39199"
      }, 
      {
        "latitude": "38.29029", 
        "longitude": "-122.38823"
      }, 
      {
        "latitude": "38.30446", 
        "longitude": "-122.40015"
      }, 
      {
        "latitude": "38.30587", 
        "longitude": "-122.40244"
      }, 
      {
        "latitude": "38.29751", 
        "longitude": "-122.41171"
      }, 
      {
        "latitude": "38.29386", 
        "longitude": "-122.41159"
      }, 
      {
        "latitude": "38.28136", 
        "longitude": "-122.40062"
      }
    ], 
    "hazardFlag": "0", 
    "lastUpdateTime": "1508632993", 
    "estCustAffected": "79", 
    "crewCurrentStatus": "PG&E repair crew is on-site working to restore power.", 
    "longitude": "-122.4126", 
    "latitude": "38.29311", 
    "outageStartTime": "1507538827", 
    "cause": "Found a damaged power pole in the area.", 
    "outageNumber": "1902150", 
    "regionName": "Sonoma"
  }, 
  {
    "outageDevices": [
      {
        "latitude": "38.32485", 
        "longitude": "-122.43562"
      }, 
      {
        "latitude": "38.34231", 
        "longitude": "-122.43123"
      }, 
      {
        "latitude": "38.33973", 
        "longitude": "-122.44359"
      }, 
      {
        "latitude": "38.3376", 
        "longitude": "-122.4463"
      }, 
      {
        "latitude": "38.33067", 
        "longitude": "-122.45011"
      }, 
      {
        "latitude": "38.32601", 
        "longitude": "-122.44541"
      }
    ], 
    "hazardFlag": "0", 
    "longitude": "-122.43206", 
    "lastUpdateTime": "1508662280", 
    "estCustAffected": "22", 
    "crewCurrentStatus": "PG&E assessment crew is en route to the outage.", 
    "crewEta": "1508690760", 
    "latitude": "38.32685", 
    "outageStartTime": "1508634841", 
    "cause": "Unknown - PG&E is investigating the cause.", 
    "outageNumber": "1907004", 
    "regionName": "Sonoma"
  }, 
  {
    "outageDevices": [
      {
        "latitude": "38.30293", 
        "longitude": "-122.43707"
      }, 
      {
        "latitude": "38.30418", 
        "longitude": "-122.43415"
      }, 
      {
        "latitude": "38.32018", 
        "longitude": "-122.41387"
      }, 
      {
        "latitude": "38.32209", 
        "longitude": "-122.41692"
      }, 
      {
        "latitude": "38.32282", 
        "longitude": "-122.41876"
      }, 
      {
        "latitude": "38.32278", 
        "longitude": "-122.41962"
      }, 
      {
        "latitude": "38.32142", 
        "longitude": "-122.42826"
      }, 
      {
        "latitude": "38.31435", 
        "longitude": "-122.43426"
      }, 
      {
        "latitude": "38.30707", 
        "longitude": "-122.44037"
      }, 
      {
        "latitude": "38.30647", 
        "longitude": "-122.44053"
      }, 
      {
        "latitude": "38.30459", 
        "longitude": "-122.44073"
      }
    ], 
    "hazardFlag": "1", 
    "lastUpdateTime": "1508609647", 
    "estCustAffected": "60", 
    "crewCurrentStatus": "PG&E is sending a repair crew to the outage location.", 
    "longitude": "-122.45795", 
    "latitude": "38.2918", 
    "outageStartTime": "1507530841", 
    "cause": "Found a damaged power pole in the area.", 
    "outageNumber": "1900530", 
    "regionName": "Sonoma"
  }, 
  {
    "currentEtor": "1508731200", 
    "outageDevices": [
      {
        "latitude": "38.2896", 
        "longitude": "-122.40016"
      }, 
      {
        "latitude": "38.29248", 
        "longitude": "-122.39576"
      }, 
      {
        "latitude": "38.29068", 
        "longitude": "-122.40146"
      }
    ], 
    "hazardFlag": "0", 
    "lastUpdateTime": "1508444642", 
    "estCustAffected": "5", 
    "crewCurrentStatus": "PG&E repair crew is on-site working to restore power.", 
    "longitude": "-122.3979", 
    "latitude": "38.29095", 
    "outageStartTime": "1507538827", 
    "cause": "Found a broken power pole in the area", 
    "outageNumber": "1902041", 
    "regionName": "Sonoma"
  }, 
  {
    "currentEtor": "1508692500", 
    "hazardFlag": "1", 
    "lastUpdateTime": "1508682688", 
    "autoEtor": "1508692500", 
    "estCustAffected": "1", 
    "crewCurrentStatus": "PG&E assessment crew is en route to the outage.", 
    "longitude": "-122.42679", 
    "latitude": "37.64453", 
    "outageStartTime": "1508681723", 
    "cause": "Unknown - PG&E will be assessing the cause.", 
    "outageNumber": "1907117", 
    "regionName": "South San Francisco"
  }, 
  {
    "currentEtor": "1508697000", 
    "hazardFlag": "1", 
    "longitude": "-121.94937", 
    "lastUpdateTime": "1508687516", 
    "autoEtor": "1508697000", 
    "crewEta": "1508688780", 
    "crewCurrentStatus": "PG&E is assessing the cause at the outage location.", 
    "estCustAffected": "7", 
    "latitude": "38.36861", 
    "outageStartTime": "1508686037", 
    "cause": "There is a problem with the transformer.", 
    "outageNumber": "1907132", 
    "regionName": "Vacaville"
  }, 
  {
    "outageDevices": [
      {
        "latitude": "38.5005", 
        "longitude": "-122.82849"
      }, 
      {
        "latitude": "38.51083", 
        "longitude": "-122.82317"
      }, 
      {
        "latitude": "38.51284", 
        "longitude": "-122.82687"
      }, 
      {
        "latitude": "38.51597", 
        "longitude": "-122.84202"
      }, 
      {
        "latitude": "38.51579", 
        "longitude": "-122.84389"
      }, 
      {
        "latitude": "38.51403", 
        "longitude": "-122.85167"
      }, 
      {
        "latitude": "38.50286", 
        "longitude": "-122.85829"
      }
    ], 
    "hazardFlag": "0", 
    "lastUpdateTime": "1508688079", 
    "estCustAffected": "96", 
    "crewCurrentStatus": "PG&E is assessing the cause at the outage location.", 
    "longitude": "-122.82237", 
    "latitude": "38.51083", 
    "outageStartTime": "1508682780", 
    "cause": "Unknown - PG&E is investigating the cause.", 
    "outageNumber": "1907125", 
    "regionName": "Windsor"
  }, 
  {
    "hazardFlag": "1", 
    "lastUpdateTime": "1508688119", 
    "estCustAffected": "1", 
    "crewCurrentStatus": "PG&E has assigned a crew to assess the outage.", 
    "longitude": "-122.64335", 
    "latitude": "38.00847", 
    "outageStartTime": "1508688115", 
    "cause": "Unknown - PG&E will be assessing the cause.", 
    "outageNumber": "1907141", 
    "regionName": "Woodacre"
  }
]