[
  {
    "etr": "2:00pm on 11/10/17 (estimated)", 
    "status": "We're aware of the outage", 
    "nbrCust": 7, 
    "reason": "Pending Investigation", 
    "lat": 28.1119985855013, 
    "lng": -82.4584680893253
  }, 
  {
    "etr": "1:30pm on 11/10/17 (estimated)", 
    "status": "We're aware of the outage", 
    "nbrCust": 31, 
    "reason": "Pending Investigation", 
    "lat": 28.0499747852804, 
    "lng": -82.361719164149
  }, 
  {
    "etr": "2:45pm on 11/10/17 (estimated)", 
    "status": "We're on our way to investigate", 
    "nbrCust": 4, 
    "reason": "Pending Investigation", 
    "lat": 27.9416294473213, 
    "lng": -82.5200442231548
  }, 
  {
    "etr": "1:00pm on 11/10/17 (estimated)", 
    "status": "We're on our way to investigate", 
    "nbrCust": 13, 
    "reason": "Pending Investigation", 
    "lat": 28.0347431888314, 
    "lng": -82.4712155386256
  }, 
  {
    "etr": "2:00pm on 11/10/17 (estimated)", 
    "status": "We're on our way to investigate", 
    "nbrCust": 31, 
    "reason": "Pending Investigation", 
    "lat": 27.9595123827025, 
    "lng": -82.3168558358761
  }, 
  {
    "etr": "1:45pm on 11/10/17 (estimated)", 
    "status": "We're on our way to investigate", 
    "nbrCust": 2, 
    "reason": "Pending Investigation", 
    "lat": 27.8750848609603, 
    "lng": -82.3597560218486
  }, 
  {
    "etr": "1:15pm on 11/10/17 (estimated)", 
    "status": "We're on our way to investigate", 
    "nbrCust": 11, 
    "reason": "Pending Investigation", 
    "lat": 27.7158748576338, 
    "lng": -82.4284700879704
  }, 
  {
    "etr": "1:30pm on 11/10/17 (estimated)", 
    "status": "We're on our way to investigate", 
    "nbrCust": 7, 
    "reason": "Pending Investigation", 
    "lat": 27.7117481165406, 
    "lng": -82.3014621037288
  }
]